{"version": 0.6, "generator": "Overpass API 0.7.62.8 e802775f", "osm3s": {"timestamp_osm_base": "2025-10-14T12:11:59Z", "copyright": "The data included in this document is from www.openstreetmap.org. The data is made available under ODbL."}, "elements": [{"type": "node", "id": 6914937590, "lat": 8.8695859, "lon": 77.4940838, "tags": {"addr:district": "Tirunelveli", "addr:full": "13/549,B,Tenkasi Main Road, Alangulam", "addr:postcode": "627851", "addr:state": "Tamil Nadu", "amenity": "hospital", "healthcare": "hospital", "name": "Sri Ram Hospital, Tirunelveli", "source": "OpenGovernmentData"}}, {"type": "node", "id": 6936695210, "lat": 8.7046869, "lon": 77.457355, "tags": {"addr:district": "Tirunelveli", "addr:full": "4A, Near Ammaiyappar Temble, Ambasamudram, Ammaiyappar Koil St", "addr:postcode": "627401", "addr:state": "Tamil Nadu", "amenity": "clinic", "healthcare": "clinic", "name": "Subham Nursing Home, Tirunelveli", "source": "OpenGovernmentData"}}, {"type": "node", "id": 6937041432, "lat": 8.7042733, "lon": 77.4560527, "tags": {"addr:district": "Tirunelveli", "addr:full": "33, West Car Street Ambasamudram Ambasamudram", "addr:postcode": "627401", "addr:state": "Tamil Nadu", "amenity": "clinic", "healthcare": "clinic", "name": "Dr Ramanujam Nursing Home And Poly Clinic", "source": "OpenGovernmentData"}}, {"type": "node", "id": 7249356834, "lat": 8.7400328, "lon": 77.5221934, "tags": {"addr:block": "Pappakudi", "addr:district": "Tirunelveli", "addr:full": "Eb Office, Anna Nagar, Alangulam Road", "addr:postcode": "627601", "addr:state": "Tamil Nadu", "addr:subdistrict": "Ambasamudram", "amenity": "hospital", "name": "Government Hospital, Sokkalal", "source": "OpenGovernmentData"}}, {"type": "node", "id": 7249356841, "lat": 8.883598, "lon": 77.388918, "tags": {"addr:block": "Sankarankoil Mpty", "addr:district": "Tirunelveli", "addr:full": "9/174, Keelapavoor, Chithambara Nadar Street, Avudayanoor", "addr:postcode": "627808", "addr:state": "Tamil Nadu", "amenity": "hospital", "name": "C. J. Hospital", "source": "OpenGovernmentData"}}, {"type": "node", "id": 7249356877, "lat": 8.7028117, "lon": 77.4579979, "tags": {"addr:district": "Tirunelveli", "addr:full": "Solaipuram, Ambasamudram", "addr:postcode": "627401", "addr:state": "Tamil Nadu", "addr:subdistrict": "Ambasamudram", "amenity": "hospital", "healthcare": "hospital", "name": "Government Hospital, Ambasamudram", "source": "OpenGovernmentData"}}, {"type": "node", "id": 7249356880, "lat": 8.6930873, "lon": 77.5196622, "tags": {"addr:block": "Cheranmadevi", "addr:district": "Tirunelveli", "addr:full": "91 B, Busstand, Veeravanallur, Bharathiyar Nagar", "addr:postcode": "627426", "addr:state": "Tamil Nadu", "amenity": "clinic", "healthcare": "clinic", "name": "S.K.R Clinic", "source": "OpenGovernmentData"}}, {"type": "node", "id": 7249356914, "lat": 8.7004812, "lon": 77.4521408, "tags": {"addr:district": "Tirunelveli", "addr:full": "Solaipuram, Ambasamudram", "addr:postcode": "627401", "addr:state": "Tamil Nadu", "addr:subdistrict": "Ambasamudram", "amenity": "clinic", "healthcare": "clinic", "name": "Lakshmi Nursing Home", "source": "OpenGovernmentData"}}, {"type": "node", "id": 7249356915, "lat": 8.867049, "lon": 77.49199, "tags": {"addr:block": "Alangulam", "addr:district": "Tirunelveli", "addr:full": "Shri Murugan Kovil, Alangulam", "addr:postcode": "627851", "addr:state": "Tamil Nadu", "addr:subdistrict": "Veerakeralamputhur", "amenity": "hospital", "healthcare": "hospital", "name": "Government Hospital, Alangulam", "source": "OpenGovernmentData"}}, {"type": "node", "id": 7249356917, "lat": 8.6908972, "lon": 77.5252827, "tags": {"addr:block": "Cheranmadevi", "addr:district": "Tirunelveli", "addr:full": "Veeravanallur PHC, Near St. Joseph Cherch, Veeravanallur, Ambai Main Road", "addr:postcode": "627426", "addr:state": "Tamil Nadu", "addr:subdistrict": "Ambasamudram", "amenity": "hospital", "healthcare": "hospital", "name": "Veeravanallur Government Hospital", "source": "OpenGovernmentData"}}, {"type": "node", "id": 7249356920, "lat": 8.682902, "lon": 77.563989, "tags": {"addr:block": "Cheranmadevi", "addr:district": "Tirunelveli", "addr:full": "Near Bus Stand, Cheranmahadevi, Vadakku Mettu Theru", "addr:postcode": "627414", "addr:state": "Tamil Nadu", "addr:subdistrict": "Ambasamudram", "amenity": "hospital", "healthcare": "hospital", "name": "Government Hospital, Cheranmahadevi", "source": "OpenGovernmentData"}}, {"type": "node", "id": 7249356926, "lat": 8.7094475, "lon": 77.4088764, "tags": {"addr:district": "Tirunelveli", "addr:full": "5/342A, Near Sivanthipuram Name Board, Shivanthipuram, Papanasam Main Road", "addr:postcode": "627425", "addr:state": "Tamil Nadu", "addr:subdistrict": "Ambasamudram", "amenity": "clinic", "name": "Chandra Nursing Home", "source": "OpenGovernmentData"}}, {"type": "node", "id": 7249356948, "lat": 8.9140846, "lon": 77.5274798, "tags": {"addr:block": "Alangulam", "addr:district": "Tirunelveli", "addr:full": "Near Socity Office, Nettur, Main Road ,Nettur", "addr:postcode": "627854", "addr:state": "Tamil Nadu", "addr:subdistrict": "Veerakeralamputhur", "amenity": "hospital", "name": "Nettur Government Hospital", "source": "OpenGovernmentData"}}, {"type": "node", "id": 7249356971, "lat": 8.7761606, "lon": 77.4214125, "tags": {"addr:district": "Tirunelveli", "addr:full": "2/36A, Tearadi Near, Vadakku Pappankulam, South Street", "addr:postcode": "627423", "addr:state": "Tamil Nadu", "addr:subdistrict": "Ambasamudram", "amenity": "hospital", "check_date": "2024-04-11", "healthcare": "hospital", "name": "Government Hospital, Vadakupappankulam", "operator:type": "government", "source": "OpenGovernmentData"}}, {"type": "node", "id": 7249356982, "lat": 8.6886524, "lon": 77.463876, "tags": {"addr:block": "Cheranmadevi", "addr:district": "Tirunelveli", "addr:full": "Kallidaikurchi", "addr:postcode": "627416", "addr:state": "Tamil Nadu", "amenity": "hospital", "healthcare": "hospital", "name": "Gomathy Hospital", "source": "OpenGovernmentData"}}, {"type": "node", "id": 7249356990, "lat": 8.7146591, "lon": 77.3859391, "tags": {"addr:district": "Tirunelveli", "addr:full": "Vikramasingapuram PHC, Liabrery, V.K.Puram, Papanasam Main Road", "addr:postcode": "627425", "addr:state": "Tamil Nadu", "addr:subdistrict": "Ambasamudram", "amenity": "hospital", "healthcare": "hospital", "name": "Vickramasingapuram,Government Hospital", "source": "OpenGovernmentData"}}, {"type": "node", "id": 7249356992, "lat": 8.7048852, "lon": 77.4564384, "tags": {"addr:district": "Tirunelveli", "addr:full": "Arts College, Ambasamudram, High School Road", "addr:postcode": "627491", "addr:state": "Tamil Nadu", "addr:subdistrict": "Ambasamudram", "amenity": "clinic", "healthcare": "clinic", "name": "Seethalakshmi Nursing Home", "source": "OpenGovernmentData"}}, {"type": "node", "id": 7843768404, "lat": 8.684624, "lon": 77.566228, "tags": {"addr:district": "Tirunelveli", "addr:full": "Cheranmahadevi", "addr:postcode": "627414", "addr:state": "Tamil Nadu", "amenity": "hospital", "healthcare": "hospital", "name": "Mohindeen Hospital", "source": "Local Knowledge"}}, {"type": "node", "id": 7843768405, "lat": 8.686157, "lon": 77.461549, "tags": {"addr:district": "Tirunelveli", "addr:full": "Kallidaikurchi", "addr:postcode": "627416", "addr:state": "Tamil Nadu", "amenity": "clinic", "healthcare": "clinic", "name": "Bogar Siddha Clinic", "source": "Local Knowledge"}}, {"type": "node", "id": 7843768407, "lat": 8.826839, "lon": 77.374085, "tags": {"addr:district": "Tirunelveli", "addr:full": "Kilakadayam", "addr:postcode": "627415", "addr:state": "Tamil Nadu", "amenity": "hospital", "healthcare": "hospital", "name": "Nimrate Hospitam", "source": "Local Knowledge"}}, {"type": "node", "id": 7843768408, "lat": 8.692185, "lon": 77.461732, "tags": {"addr:district": "Tirunelveli", "addr:full": "Kallidaikurchi", "addr:postcode": "627416", "addr:state": "Tamil Nadu", "amenity": "hospital", "healthcare": "hospital", "name": "Elayaraja Orthopaedic Hospital", "source": "Local Knowledge", "wheelchair": "yes"}}, {"type": "node", "id": 7843768409, "lat": 8.714397, "lon": 77.385855, "tags": {"addr:district": "Tirunelveli", "addr:full": "Vickramasingapuram", "addr:postcode": "627425", "addr:state": "Tamil Nadu", "amenity": "hospital", "healthcare": "hospital", "name": "Arun Hospital", "source": "Local Knowledge"}}, {"type": "node", "id": 7843768410, "lat": 8.6819991, "lon": 77.4668871, "tags": {"addr:district": "Tirunelveli", "addr:full": "Kallidaikurchi", "addr:postcode": "627416", "addr:state": "Tamil Nadu", "amenity": "hospital", "healthcare": "hospital", "name": "Kanna Hospital", "source": "Local Knowledge"}}, {"type": "node", "id": 7843768411, "lat": 8.8239964, "lon": 77.3742084, "tags": {"addr:district": "Tirunelveli", "addr:full": "Kadayam", "addr:postcode": "627415", "addr:state": "Tamil Nadu", "amenity": "hospital", "healthcare": "hospital", "name": "Nimrod Hospital", "source": "Local Knowledge"}}, {"type": "node", "id": 7843768412, "lat": 8.718179, "lon": 77.383002, "tags": {"addr:district": "Tirunelveli", "addr:full": "Vickramasingapuram", "addr:postcode": "627425", "addr:state": "Tamil Nadu", "amenity": "hospital", "healthcare": "hospital", "name": "Chandra Nursing Home", "source": "Local Knowledge"}}, {"type": "node", "id": 7843768413, "lat": 8.757511, "lon": 77.507067, "tags": {"addr:district": "Tirunelveli", "addr:full": "Pappakudi", "addr:postcode": "627602", "addr:state": "Tamil Nadu", "amenity": "hospital", "name": "Ayya Kovil", "source": "Local Knowledge"}}, {"type": "node", "id": 7843768416, "lat": 8.7094163, "lon": 77.4099478, "tags": {"addr:district": "Tirunelveli", "addr:full": "Sivanthipuram, ambasamuthiram, Papanasam", "addr:postcode": "627425", "addr:state": "Tamil Nadu", "amenity": "clinic", "name": "Acupuncture Clinic", "source": "Local Knowledge"}}, {"type": "node", "id": 7843768417, "lat": 8.714996, "lon": 77.37231, "tags": {"addr:district": "Tirunelveli", "addr:full": "Dana, Papanasam", "addr:postcode": "627425", "addr:state": "Tamil Nadu", "amenity": "hospital", "name": "Aviztham Siddha Hospital", "source": "Local Knowledge"}}, {"type": "node", "id": 7843768423, "lat": 8.7143432, "lon": 77.3865614, "tags": {"addr:district": "Tirunelveli", "addr:full": "Vickramasingapuram", "addr:postcode": "627425", "addr:state": "Tamil Nadu", "amenity": "clinic", "healthcare": "clinic", "name": "Athi Sakthi Clinic", "source": "Local Knowledge"}}, {"type": "node", "id": 7843768426, "lat": 8.7044495, "lon": 77.4562408, "tags": {"addr:district": "Tirunelveli", "addr:full": "New Colony, Ambasamudram", "addr:postcode": "627401", "addr:state": "Tamil Nadu", "amenity": "hospital", "healthcare": "hospital", "name": "Pandian Hospital", "source": "Local Knowledge"}}, {"type": "node", "id": 7843768429, "lat": 8.696885, "lon": 77.518804, "tags": {"addr:district": "Tirunelveli", "addr:full": "Veeravanallur", "addr:postcode": "627426", "addr:state": "Tamil Nadu", "amenity": "hospital", "healthcare": "hospital", "name": "Lakshmi Hospital", "source": "Local Knowledge"}}, {"type": "node", "id": 7843768430, "lat": 8.737123, "lon": 77.5194776}, {"type": "node", "id": 7843768431, "lat": 8.6802817, "lon": 77.5604769, "tags": {"addr:district": "Tirunelveli", "addr:full": "Pallivasal, Cheranmahadevi", "addr:postcode": "627414", "addr:state": "Tamil Nadu", "amenity": "hospital", "healthcare": "hospital", "name": "BMK Siddha Hospital", "source": "Local Knowledge"}}, {"type": "node", "id": 7843768432, "lat": 8.704838, "lon": 77.458776, "tags": {"addr:district": "Tirunelveli", "addr:full": "Ambasamudram", "addr:postcode": "627401", "addr:state": "Tamil Nadu", "amenity": "hospital", "healthcare": "hospital", "name": "Azeez Hospital", "source": "Local Knowledge"}}, {"type": "node", "id": 7843768437, "lat": 8.713143, "lon": 77.393576, "tags": {"addr:district": "Tirunelveli", "addr:postcode": "627425", "addr:state": "Tamil Nadu", "amenity": "hospital", "name": "Subhalakshmi Hospital", "source": "Local Knowledge"}}, {"type": "node", "id": 7843768440, "lat": 8.6958207, "lon": 77.5198787, "tags": {"addr:district": "Tirunelveli", "addr:full": "Veeravanallur", "addr:postcode": "627426", "addr:state": "Tamil Nadu", "amenity": "hospital", "healthcare": "hospital", "name": "Dhanvantri Hospital", "source": "Local Knowledge"}}, {"type": "node", "id": 7843768442, "lat": 8.68886, "lon": 77.463309, "tags": {"addr:district": "Tirunelveli", "addr:full": "Kallidaikurchi", "addr:postcode": "627416", "addr:state": "Tamil Nadu", "amenity": "hospital", "healthcare": "hospital", "name": "Aravind Eye Care Hospital", "source": "Local Knowledge"}}, {"type": "node", "id": 7843768444, "lat": 8.743359, "lon": 77.524347, "tags": {"addr:district": "Tirunelveli", "addr:full": "Mukkudal", "addr:postcode": "627601", "addr:state": "Tamil Nadu", "amenity": "clinic", "name": "Aravind Vision Centre", "source": "Local Knowledge"}}, {"type": "node", "id": 7843768445, "lat": 8.822265, "lon": 77.372346, "tags": {"addr:district": "Tirunelveli", "addr:full": "Kadayam", "addr:postcode": "627415", "addr:state": "Tamil Nadu", "amenity": "hospital", "healthcare": "hospital", "name": "Sugam Hospital", "source": "Local Knowledge"}}, {"type": "node", "id": 7843768447, "lat": 8.6826012, "lon": 77.5649361, "tags": {"addr:district": "Tirunelveli", "addr:full": "Pallivasal, Cheranmahadevi", "addr:postcode": "627414", "addr:state": "Tamil Nadu", "amenity": "doctors", "healthcare": "doctor", "name": "Dr. John Singh", "source": "Local Knowledge"}}, {"type": "node", "id": 7843768449, "lat": 8.703657, "lon": 77.44895, "tags": {"addr:district": "Tirunelveli", "addr:full": "Ambasamudram", "addr:postcode": "627401", "addr:state": "Tamil Nadu", "amenity": "clinic", "healthcare": "clinic", "name": "Sri Ramakrishna Siddha Health Care", "source": "Local Knowledge"}}, {"type": "node", "id": 7843768450, "lat": 8.684954, "lon": 77.461809, "tags": {"addr:district": "Tirunelveli", "addr:full": "Kallidaikurchi", "addr:postcode": "627416", "addr:state": "Tamil Nadu", "amenity": "hospital", "healthcare": "hospital", "name": "Damayanthi Hospital", "source": "Local Knowledge"}}, {"type": "node", "id": 7843768451, "lat": 8.703722, "lon": 77.4495772, "tags": {"addr:district": "Tirunelveli", "addr:full": "Ambasamudram", "addr:postcode": "627401", "addr:state": "Tamil Nadu", "amenity": "hospital", "healthcare": "hospital", "name": "Anandha Jothi Hospital", "source": "Local Knowledge"}}, {"type": "node", "id": 7843768454, "lat": 8.7034288, "lon": 77.4488879, "tags": {"addr:district": "Tirunelveli", "addr:full": "Ambasamudram", "addr:postcode": "627401", "addr:state": "Tamil Nadu", "amenity": "clinic", "healthcare": "clinic", "name": "Dr. Kumar Children's Clinic", "source": "Local Knowledge"}}, {"type": "node", "id": 7843768455, "lat": 8.69244, "lon": 77.520877, "tags": {"addr:district": "Tirunelveli", "addr:full": "Veeravanallur", "addr:postcode": "627426", "addr:state": "Tamil Nadu", "amenity": "clinic", "healthcare": "clinic", "name": "Sathya Clinic", "source": "Local Knowledge"}}, {"type": "node", "id": 7843768456, "lat": 8.701266, "lon": 77.460029, "tags": {"addr:district": "Tirunelveli", "addr:full": "Solaipuram, Ambasamudram", "addr:postcode": "627401", "addr:state": "Tamil Nadu", "amenity": "hospital", "healthcare": "hospital", "name": "Sakthi Nursing Home", "source": "Local Knowledge", "wheelchair": "yes"}}, {"type": "node", "id": 7843768457, "lat": 8.827374, "lon": 77.373559, "tags": {"addr:district": "Tirunelveli", "addr:full": "Kadayam", "addr:postcode": "627415", "addr:state": "Tamil Nadu", "amenity": "hospital", "healthcare": "hospital", "name": "Anbu Hospital,", "source": "Local Knowledge"}}, {"type": "node", "id": 7843768459, "lat": 8.707371, "lon": 77.440642, "tags": {"addr:district": "Tirunelveli", "addr:postcode": "627428", "addr:state": "Tamil Nadu", "amenity": "doctors", "healthcare": "doctor", "name": "Dr. M. Diwan Mohideen", "source": "Local Knowledge"}}, {"type": "node", "id": 7843768460, "lat": 8.694761, "lon": 77.519646, "tags": {"addr:district": "Tirunelveli", "addr:full": "Veeravanallur", "addr:postcode": "627426", "addr:state": "Tamil Nadu", "amenity": "hospital", "healthcare": "hospital", "name": "Kumarasamy Hospital", "source": "Local Knowledge"}}, {"type": "node", "id": 7843768461, "lat": 8.6886306, "lon": 77.4615642, "tags": {"addr:district": "Tirunelveli", "addr:full": "Kallidaikurchi", "addr:postcode": "627416", "addr:state": "Tamil Nadu", "amenity": "hospital", "healthcare": "hospital", "name": "Sigaram Siddha Hospital", "source": "Local Knowledge"}}, {"type": "node", "id": 7843768463, "lat": 8.687461, "lon": 77.566403, "tags": {"addr:district": "Tirunelveli", "addr:full": "Cheranmahadevi", "addr:postcode": "627414", "addr:state": "Tamil Nadu", "amenity": "hospital", "healthcare": "hospital", "name": "Indra Hospital", "source": "Local Knowledge"}}, {"type": "node", "id": 7843768464, "lat": 8.7453897, "lon": 77.52314, "tags": {"addr:district": "Tirunelveli", "addr:full": "Mukkudal", "addr:postcode": "627601", "addr:state": "Tamil Nadu", "amenity": "hospital", "name": "Pushpam Memorial Hospital", "source": "Local Knowledge"}}, {"type": "node", "id": 7843768468, "lat": 8.740501, "lon": 77.522546, "tags": {"addr:district": "Tirunelveli", "addr:full": "Mukkudal", "addr:postcode": "627601", "addr:state": "Tamil Nadu", "amenity": "hospital", "name": "Krishna Hospital", "source": "Local Knowledge"}}, {"type": "node", "id": 7843768471, "lat": 8.7126691, "lon": 77.3946823, "tags": {"addr:district": "Tirunelveli", "addr:full": "Vickramasingapuram", "addr:postcode": "627425", "addr:state": "Tamil Nadu", "amenity": "hospital", "check_date": "2024-04-12", "healthcare": "hospital", "name": "ESI Hospital", "operator": "Employees' State Insurance", "operator:short": "ESI", "operator:type": "public", "operator:wikidata": "Q3595726", "source": "Local Knowledge"}}, {"type": "node", "id": 7843768472, "lat": 8.703561, "lon": 77.458439, "tags": {"addr:district": "Tirunelveli", "addr:full": "Ambasamudram", "addr:postcode": "627401", "addr:state": "Tamil Nadu", "amenity": "clinic", "healthcare": "clinic", "name": "KK Siddha Clinic", "source": "Local Knowledge"}}, {"type": "node", "id": 7843768474, "lat": 8.714802, "lon": 77.384013, "tags": {"addr:district": "Tirunelveli", "addr:full": "Vickramasingapuram", "addr:postcode": "627425", "addr:state": "Tamil Nadu", "amenity": "hospital", "healthcare": "hospital", "name": "Chandra Sekar Hospital", "source": "Local Knowledge"}}, {"type": "node", "id": 7843768475, "lat": 8.7035582, "lon": 77.4498042, "tags": {"addr:district": "Tirunelveli", "addr:full": "Ambasamudram", "addr:postcode": "627401", "addr:state": "Tamil Nadu", "amenity": "hospital", "healthcare": "hospital", "name": "Jessie Eye Hospital", "source": "Local Knowledge"}}, {"type": "node", "id": 7843768477, "lat": 8.7140937, "lon": 77.3871669, "tags": {"addr:district": "Tirunelveli", "addr:full": "Vickramasingapuram", "addr:postcode": "627425", "addr:state": "Tamil Nadu", "amenity": "clinic", "healthcare": "clinic", "name": "Rajam Clinic", "source": "Local Knowledge"}}, {"type": "node", "id": 7843768478, "lat": 8.688891, "lon": 77.461203, "tags": {"addr:district": "Tirunelveli", "addr:full": "Kallidaikurchi", "addr:postcode": "627416", "addr:state": "Tamil Nadu", "amenity": "hospital", "healthcare": "hospital", "name": "Dr. Muthukumar Hospital", "source": "Local Knowledge"}}, {"type": "node", "id": 7843768480, "lat": 8.8235761, "lon": 77.3737701, "tags": {"addr:district": "Tirunelveli", "addr:full": "Kadayam.", "addr:state": "Tamil Nadu", "amenity": "hospital", "healthcare": "hospital", "name": "Maris Siddha Hospltal", "source": "Local Knowledge"}}, {"type": "node", "id": 7843768481, "lat": 8.70583, "lon": 77.44052, "tags": {"addr:district": "Tirunelveli", "addr:postcode": "627401", "addr:state": "Tamil Nadu", "amenity": "hospital", "healthcare": "hospital", "name": "Kerala Arogya Ayurveda Panchakarama Hospital", "source": "Local Knowledge"}}, {"type": "node", "id": 7843768482, "lat": 8.70404, "lon": 77.4561799, "tags": {"addr:district": "Tirunelveli", "addr:full": "Ambasamudram", "addr:postcode": "627401", "addr:state": "Tamil Nadu", "amenity": "hospital", "healthcare": "hospital", "name": "Raja Pandian Hospital", "source": "Local Knowledge"}}, {"type": "node", "id": 7843768485, "lat": 8.704138, "lon": 77.45877, "tags": {"addr:district": "Tirunelveli", "addr:full": "Ambasamudram", "addr:postcode": "627401", "addr:state": "Tamil Nadu", "amenity": "hospital", "healthcare": "hospital", "name": "Dr. Sankaranarayanan Hospital", "source": "Local Knowledge"}}, {"type": "node", "id": 7843768486, "lat": 8.703363, "lon": 77.458363, "tags": {"addr:district": "Tirunelveli", "addr:full": "Solaipuram, Ambasamudram", "addr:postcode": "627401", "addr:state": "Tamil Nadu", "amenity": "hospital", "healthcare": "hospital", "name": "Santha Hospital", "source": "Local Knowledge"}}, {"type": "node", "id": 7843768492, "lat": 8.7110877, "lon": 77.4002799, "tags": {"addr:district": "Tirunelveli", "addr:full": "Ambalavanapuram, Vickramasingapuram", "addr:postcode": "627425", "addr:state": "Tamil Nadu", "amenity": "clinic", "name": "Manuel Physiotherapy Clinic", "source": "Local Knowledge"}}, {"type": "node", "id": 7844921930, "lat": 8.5681052, "lon": 77.4096562, "tags": {"addr:district": "Tirunelveli", "addr:postcode": "627420", "addr:state": "Tamil Nadu", "amenity": "hospital", "name": "BBTCL Hospital", "source": "Local Knowledge"}}, {"type": "node", "id": 7849699475, "lat": 8.912588, "lon": 77.479867, "tags": {"addr:district": "Tenkasi", "addr:full": "Sivalingapuram", "addr:postcode": "627853", "addr:state": "Tamil Nadu", "amenity": "hospital", "name": "SLP City Government Hospital", "source": "Local Knowledge"}}, {"type": "node", "id": 7849699489, "lat": 8.877252, "lon": 77.391306, "tags": {"addr:district": "Tenkasi", "addr:postcode": "627415", "addr:state": "Tamil Nadu", "amenity": "hospital", "name": "Government Hospital", "source": "Local Knowledge"}}, {"type": "node", "id": 7849699494, "lat": 8.899049, "lon": 77.404527, "tags": {"addr:district": "Tenkasi", "addr:full": "Keezhapavur", "addr:postcode": "627808", "addr:state": "Tamil Nadu", "amenity": "hospital", "name": "MGS Hospital", "source": "Local Knowledge"}}, {"type": "node", "id": 7849699544, "lat": 8.878323, "lon": 77.382413, "tags": {"addr:district": "Tenkasi", "addr:full": "Avudaiyanoor", "addr:postcode": "627415", "addr:state": "Tamil Nadu", "amenity": "clinic", "name": "Annai Clinic and Eye Hospital", "source": "Local Knowledge"}}, {"type": "node", "id": 7849819522, "lat": 8.864656, "lon": 77.496001, "tags": {"addr:district": "Tenkasi", "addr:full": "Alangulam", "addr:postcode": "627851", "addr:state": "Tamil Nadu", "amenity": "hospital", "healthcare": "hospital", "name": "Jeyaram Hospital", "source": "Local Knowledge"}}, {"type": "node", "id": 7849819533, "lat": 8.8645538, "lon": 77.4955716, "tags": {"addr:district": "Tenkasi", "addr:full": "Alangulam", "addr:postcode": "627851", "addr:state": "Tamil Nadu", "amenity": "hospital", "healthcare": "hospital", "name": "Maniram Hospital", "source": "Local Knowledge"}}, {"type": "node", "id": 7849819544, "lat": 8.868568, "lon": 77.492429, "tags": {"addr:district": "Tenkasi", "addr:postcode": "627851", "addr:state": "Tamil Nadu", "amenity": "hospital", "healthcare": "hospital", "name": "Mani Hospital", "source": "Local Knowledge"}}, {"type": "node", "id": 7849819549, "lat": 8.930966, "lon": 77.568949, "tags": {"addr:district": "Tenkasi", "addr:full": "Venkateshaypuram", "addr:postcode": "627854", "addr:state": "Tamil Nadu", "amenity": "hospital", "name": "Tamilselvan Hospital", "source": "Local Knowledge"}}, {"type": "node", "id": 7849819556, "lat": 8.865063, "lon": 77.494974, "tags": {"addr:district": "Tenkasi", "addr:full": "Kattabo, Alangulam", "addr:postcode": "627851", "addr:state": "Tamil Nadu", "amenity": "hospital", "healthcare": "hospital", "name": "Vasantham Hospital", "source": "Local Knowledge"}}, {"type": "node", "id": 7849819565, "lat": 8.8674485, "lon": 77.4951666, "tags": {"addr:district": "Tenkasi", "addr:full": "Alangulam", "addr:postcode": "627851", "addr:state": "Tamil Nadu", "amenity": "hospital", "healthcare": "hospital", "name": "Jayalakshmi Multi Speciality Hospital", "source": "Local Knowledge"}}, {"type": "node", "id": 7849819570, "lat": 8.8675263, "lon": 77.4922339, "tags": {"addr:district": "Tenkasi", "addr:full": "Alangulam, Tirunelveli", "addr:postcode": "627851", "addr:state": "Tamil Nadu", "amenity": "hospital", "healthcare": "hospital", "name": "Community Hospital", "source": "Local Knowledge"}}, {"type": "node", "id": 7849819587, "lat": 8.8646031, "lon": 77.496207, "tags": {"addr:district": "Tenkasi", "addr:full": "Alangulam", "addr:postcode": "627851", "addr:state": "Tamil Nadu", "amenity": "hospital", "healthcare": "hospital", "name": "Rani Hospital", "source": "Local Knowledge"}}, {"type": "node", "id": 9888495886, "lat": 8.7353203, "lon": 77.5188768}, {"type": "node", "id": 9888495887, "lat": 8.7373987, "lon": 77.5182116}, {"type": "node", "id": 9888495888, "lat": 8.7357073, "lon": 77.5174391}, {"type": "way", "id": 1078660039, "nodes": [9888495888, 9888495887, 7843768430, 9888495886, 9888495888], "tags": {"addr:district": "Tirunelveli", "addr:full": "Mukkudal", "addr:postcode": "627601", "addr:state": "Tamil Nadu", "amenity": "hospital", "name": "Central Hospital For Beedi Workers", "source": "Local Knowledge"}}]}