{"version": 0.6, "generator": "Overpass API 0.7.62.8 e802775f", "osm3s": {"timestamp_osm_base": "2025-10-14T12:11:59Z", "copyright": "The data included in this document is from www.openstreetmap.org. The data is made available under ODbL."}, "elements": [{"type": "node", "id": 2145507518, "lat": 8.7262031, "lon": 77.7060546}, {"type": "node", "id": 2145507548, "lat": 8.7258876, "lon": 77.7060413}, {"type": "node", "id": 2145507579, "lat": 8.726211, "lon": 77.7058991}, {"type": "node", "id": 2145507613, "lat": 8.725877, "lon": 77.7058777}, {"type": "node", "id": 2145524951, "lat": 8.7415622, "lon": 77.7136184}, {"type": "node", "id": 2145525002, "lat": 8.7419652, "lon": 77.7137337}, {"type": "node", "id": 2145525029, "lat": 8.7422832, "lon": 77.7134629}, {"type": "node", "id": 2145525088, "lat": 8.7418723, "lon": 77.7132913}, {"type": "node", "id": 2145525120, "lat": 8.7421667, "lon": 77.7137686}, {"type": "node", "id": 2145525157, "lat": 8.7415225, "lon": 77.7137069}, {"type": "node", "id": 2145525173, "lat": 8.7418247, "lon": 77.7138678}, {"type": "node", "id": 2394940227, "lat": 8.7249013, "lon": 77.7219613, "tags": {"amenity": "hospital", "designation": "Hospital", "emergency": "yes", "healthcare": "hospital", "name": "Agarwal Eye Hospital"}}, {"type": "node", "id": 3154694818, "lat": 8.7041101, "lon": 77.7386166, "tags": {"addr:district": "Tirunelveli", "addr:full": "37,S T C Collage Road ,Perumalpuram", "addr:postcode": "627007", "addr:state": "Tamil Nadu", "amenity": "clinic", "healthcare": "clinic", "name": "Kartheek Nursing Home", "source": "OpenGovernmentData"}}, {"type": "node", "id": 3856203582, "lat": 8.7236505, "lon": 77.7216933}, {"type": "node", "id": 3856203583, "lat": 8.7236425, "lon": 77.7220634}, {"type": "node", "id": 3856203584, "lat": 8.7240269, "lon": 77.7220876}, {"type": "node", "id": 3856203586, "lat": 8.7240085, "lon": 77.7227467}, {"type": "node", "id": 3856203587, "lat": 8.723608, "lon": 77.722734}, {"type": "node", "id": 3856203588, "lat": 8.7235046, "lon": 77.7227286}, {"type": "node", "id": 3856203589, "lat": 8.7234861, "lon": 77.7216772}, {"type": "node", "id": 4764535890, "lat": 8.7622984, "lon": 77.7096196, "tags": {"amenity": "hospital", "healthcare": "hospital", "name": "Santhosh Hospital"}}, {"type": "node", "id": 6914896259, "lat": 8.697629, "lon": 77.7557065, "tags": {"addr:district": "Tirunelveli", "addr:full": "Palayamkottai", "addr:postcode": "627002", "addr:state": "Tamil Nadu", "amenity": "clinic", "healthcare": "clinic", "name": "Pushpalatha Maternity And Surgical Nursing Home", "source": "OpenGovernmentData"}}, {"type": "node", "id": 6915252063, "lat": 8.7103302, "lon": 77.7517073, "tags": {"addr:district": "Tirunelveli", "addr:full": "#7D High Ground St Thomas Road", "addr:postcode": "627011", "addr:state": "Tamil Nadu", "amenity": "hospital", "healthcare": "hospital", "name": "Vekateshwara Hospitals", "source": "OpenGovernmentData"}}, {"type": "node", "id": 6915828970, "lat": 8.7251366, "lon": 77.6877507, "tags": {"addr:district": "Madurai", "addr:full": "13,Vinayagar Kovil Street,Thirunagar", "addr:postcode": "625006", "addr:state": "Tamil Nadu", "amenity": "clinic", "healthcare": "clinic", "name": "Kanthimathi Nursing Home", "source": "OpenGovernmentData"}}, {"type": "node", "id": 6916094871, "lat": 8.7331477, "lon": 77.7220957, "tags": {"addr:district": "Tirunelveli", "addr:full": "341/2, North Bye Pass Road, Vannarpettai", "addr:postcode": "627003", "addr:state": "Tamil Nadu", "amenity": "hospital", "healthcare": "hospital", "name": "Vasan Eye Care Hospital, Tirunelveli", "source": "OpenGovernmentData"}}, {"type": "node", "id": 6926175049, "lat": 8.726199, "lon": 77.7220716, "tags": {"addr:district": "Tirunelveli", "addr:full": "Land Mark Towers, 10/1/15,South Bye Pass Road, Opp:To Bsnl,Vannarpet", "addr:postcode": "627003", "addr:state": "Tamil Nadu", "amenity": "hospital", "healthcare": "hospital", "name": "Dr Agarwal's Eye Hospital, Vannarpet", "operator": "Dr. Agarwal's Eye Hospital", "operator:wikidata": "Q17052044", "source": "OpenGovernmentData"}}, {"type": "node", "id": 6926494037, "lat": 8.7336063, "lon": 77.7231109, "tags": {"addr:district": "Tirunelveli", "addr:full": "110E/20/1, North By-Pass Road Vannarpet", "addr:postcode": "627003", "addr:state": "Tamil Nadu", "amenity": "hospital", "healthcare": "hospital", "name": "Galaxy Hospitals", "source": "OpenGovernmentData", "wheelchair": "yes"}}, {"type": "node", "id": 6927326944, "lat": 8.7249749, "lon": 77.7309939, "tags": {"addr:district": "Tirunelveli", "addr:full": "R5, Chatram St, Murugankurichi", "addr:postcode": "627002", "addr:state": "Tamil Nadu", "amenity": "hospital", "healthcare": "hospital", "name": "Dr Agnes' Joseph Hospital", "source": "OpenGovernmentData"}}, {"type": "node", "id": 6928756297, "lat": 8.7282285, "lon": 77.7232289, "tags": {"addr:district": "Tirunelveli", "addr:full": "10-B/1H/4, T.V.M Road, Vannarpettai ( Behind Iskcon Temple)", "addr:postcode": "627002", "addr:state": "Tamil Nadu", "amenity": "hospital", "healthcare": "hospital", "name": "Dr. Nambiyappan Hospitals", "source": "OpenGovernmentData"}}, {"type": "node", "id": 6928879663, "lat": 8.7195843, "lon": 77.7321111, "tags": {"addr:district": "Tirunelveli", "addr:full": "Trivandrum Road, Palayamkotta", "addr:postcode": "627002", "addr:state": "Tamil Nadu", "amenity": "hospital", "healthcare": "hospital", "name": "A.J. Hospital, Tirunelveli", "source": "OpenGovernmentData"}}, {"type": "node", "id": 6929243677, "lat": 8.736445, "lon": 77.7118262, "tags": {"addr:district": "Tirunelveli", "addr:full": "Madurai Road", "addr:postcode": "627001", "addr:state": "Tamil Nadu", "amenity": "clinic", "healthcare": "clinic", "name": "Subramaniam Nursing Home (Kidney Centre)", "source": "OpenGovernmentData"}}, {"type": "node", "id": 6929263253, "lat": 8.706572, "lon": 77.7257247, "tags": {"addr:district": "Tirunelveli", "addr:full": "50-Ab/5, Ambai Road , Kulavanigarpuram", "addr:postcode": "627001", "addr:state": "Tamil Nadu", "amenity": "hospital", "healthcare": "hospital", "name": "Sabeena Hospital", "source": "OpenGovernmentData"}}, {"type": "node", "id": 6929592135, "lat": 8.7188725, "lon": 77.7363248, "tags": {"addr:district": "Tirunelveli", "addr:full": "1-D/2,North Highground Road,Diocesan Office Campus,Palayamkootai", "addr:postcode": "627002", "addr:state": "Tamil Nadu", "amenity": "hospital", "healthcare": "hospital", "name": "Csi Jayaraj Annapackiam Mission Hospital", "source": "OpenGovernmentData"}}, {"type": "node", "id": 6932141757, "lat": 8.7000411, "lon": 77.7554175, "tags": {"addr:district": "Tirunelveli", "addr:full": "729-C, North 6Th Street, Thiyagarajanagar", "addr:postcode": "627011", "addr:state": "Tamil Nadu", "amenity": "clinic", "healthcare": "clinic", "name": "Ranjeetham Nursing Home", "source": "OpenGovernmentData"}}, {"type": "node", "id": 6933873370, "lat": 8.7250776, "lon": 77.7085827, "tags": {"addr:district": "Tirunelveli", "addr:full": "#17 E, Perumal South Car Street,Near Pvt Theatre", "addr:postcode": "627001", "addr:state": "Tamil Nadu", "amenity": "clinic", "healthcare": "clinic", "name": "Sugham Health Centre", "source": "OpenGovernmentData"}}, {"type": "node", "id": 6934120450, "lat": 8.7271323, "lon": 77.7302402, "tags": {"addr:district": "Tirunelveli", "addr:full": "Post Box No. 107, Murugankurichi Palayamkottal", "addr:postcode": "627002", "addr:state": "Tamil Nadu", "amenity": "hospital", "healthcare": "clinic", "name": "Annai Velankani Nursing Home", "opening_hours": "24/7", "phone": "04622501663", "source": "OpenGovernmentData", "website": "https://avhospitals.co.in/"}}, {"type": "node", "id": 6934270995, "lat": 8.7312177, "lon": 77.7478744, "tags": {"addr:district": "Tirunelveli", "addr:full": "Eden,10/1,Main Road, Shanthinagar, Opposite Manikoondu", "addr:postcode": "627002", "addr:state": "Tamil Nadu", "amenity": "hospital", "healthcare": "hospital", "name": "Angel Heart Centre", "source": "OpenGovernmentData"}}, {"type": "node", "id": 6934271019, "lat": 8.707401, "lon": 77.7484581, "tags": {"addr:district": "Tirunelveli", "addr:full": "122 , Kamarajpur Road ,Anbu Nagar", "addr:postcode": "627011", "addr:state": "Tamil Nadu", "amenity": "hospital", "healthcare": "hospital", "name": "Madhubala Hospital", "source": "OpenGovernmentData"}}, {"type": "node", "id": 6934334076, "lat": 8.727172, "lon": 77.7479777, "tags": {"addr:district": "Tirunelveli", "addr:full": "Tiruchendur Road, Palayamkottai", "addr:postcode": "627002", "addr:state": "Tamil Nadu", "amenity": "hospital", "healthcare": "hospital", "name": "C S I Bellpins Indrani Chelladurai Mission Hospital", "source": "OpenGovernmentData"}}, {"type": "node", "id": 6936332882, "lat": 8.7119289, "lon": 77.7507403, "tags": {"addr:district": "Tirunelveli", "addr:full": "Tirunelveli Medical College Hospital, Near District Collector Camp Office", "addr:postcode": "627008", "addr:state": "Tamil Nadu", "amenity": "hospital", "healthcare": "hospital", "name": "Tirunelveli Medical College and Hospital", "source": "OpenGovernmentData"}}, {"type": "node", "id": 6936339712, "lat": 8.7280124, "lon": 77.7222513, "tags": {"addr:district": "Tirunelveli", "addr:full": "21, Svk Chekkad St, Pettai", "addr:postcode": "627004", "addr:state": "Tamil Nadu", "amenity": "hospital", "healthcare": "hospital", "name": "Raaja Hospital", "source": "OpenGovernmentData"}}, {"type": "node", "id": 6936380669, "lat": 8.6959017, "lon": 77.739408, "tags": {"addr:district": "Tirunelveli", "addr:full": "2nd Sharon Street, Ngo Colony", "addr:postcode": "627001", "addr:state": "Tamil Nadu", "amenity": "hospital", "healthcare": "hospital", "name": "Royal Hospital For Children", "source": "OpenGovernmentData"}}, {"type": "node", "id": 6936426589, "lat": 8.7250836, "lon": 77.7179718, "tags": {"addr:district": "Tirunelveli", "addr:full": "District Science Centre Road Kokkirakulam", "addr:postcode": "627004", "addr:state": "Tamil Nadu", "amenity": "hospital", "healthcare": "hospital", "name": "Devi Hospital", "source": "OpenGovernmentData"}}, {"type": "node", "id": 6936476052, "lat": 8.7246276, "lon": 77.6876548, "tags": {"addr:district": "Tirunelveli", "addr:full": "Tirunelveli Town", "addr:postcode": "627006", "addr:state": "Tamil Nadu", "amenity": "clinic", "healthcare": "clinic", "name": "Arun Nursing Home", "source": "OpenGovernmentData"}}, {"type": "node", "id": 6936677070, "lat": 8.6951036, "lon": 77.7156933, "tags": {"addr:district": "Tirunelveli", "addr:full": "1-A, Hameempuram North Street, Melapalayam", "addr:postcode": "627005", "addr:state": "Tamil Nadu", "amenity": "hospital", "healthcare": "hospital", "name": "Selvan Hospital", "source": "OpenGovernmentData"}}, {"type": "node", "id": 6936708069, "lat": 8.72501, "lon": 77.7384652, "tags": {"addr:district": "Tirunelveli", "addr:full": "No.28, Sivan North Car Street, Palayamkottsi", "addr:postcode": "627002", "addr:state": "Tamil Nadu", "amenity": "hospital", "healthcare": "hospital", "name": "Sms Hospital, Tirunelveli", "source": "OpenGovernmentData"}}, {"type": "node", "id": 6936709025, "lat": 8.6998588, "lon": 77.7247886, "tags": {"addr:district": "Tirunelveli", "addr:full": "Tirunelveli", "addr:postcode": "627003", "addr:state": "Tamil Nadu", "amenity": "hospital", "healthcare": "hospital", "name": "Sri Sakthi Hospital", "source": "OpenGovernmentData"}}, {"type": "node", "id": 6936709126, "lat": 8.7269984, "lon": 77.7348013, "tags": {"addr:district": "Tirunelveli", "addr:full": "No 4 North High Ground Road Palayamkottai Palayamkottai", "addr:postcode": "627007", "addr:state": "Tamil Nadu", "amenity": "hospital", "healthcare": "hospital", "name": "Krishna Hospital, Tirunelveli", "source": "OpenGovernmentData"}}, {"type": "node", "id": 6936971157, "lat": 8.723404, "lon": 77.6628712, "tags": {"addr:district": "Tirunelveli", "addr:full": "180,Chermadevi Road,Pettai", "addr:postcode": "627004", "addr:state": "Tamil Nadu", "amenity": "hospital", "healthcare": "hospital", "name": "Kani Hospital", "source": "OpenGovernmentData"}}, {"type": "node", "id": 6937268472, "lat": 8.7258478, "lon": 77.7070834, "tags": {"addr:district": "Tirunelveli", "addr:full": "24/49-B, V.K.Road", "addr:postcode": "627001", "addr:state": "Tamil Nadu", "amenity": "hospital", "healthcare": "hospital", "name": "Sankar Hospital, Tirunelveli", "source": "OpenGovernmentData"}}, {"type": "node", "id": 7210920541, "lat": 8.7262514, "lon": 77.7211816, "tags": {"addr:district": "Tirunelveli", "addr:full": "4A, Near Tnstc Depo, Vannarpettai, North Bye Pass Road", "addr:postcode": "627009", "addr:state": "Tamil Nadu", "amenity": "hospital", "healthcare": "hospital", "name": "Lakshmi Madhavan Hospital", "source": "OpenGovernmentData"}}, {"type": "node", "id": 7249356826, "lat": 8.7232798, "lon": 77.7488801, "tags": {"addr:block": "Tirunelveli Corp", "addr:district": "Tirunelveli", "addr:full": "Samathanapuram Road, Palayamkottai, Tirunelveli", "addr:postcode": "627002", "addr:state": "Tamil Nadu", "amenity": "hospital", "healthcare": "hospital", "name": "Csi Bellpins Indrani Chelladurai Mission Hospital", "source": "OpenGovernmentData"}}, {"type": "node", "id": 7249356837, "lat": 8.7354558, "lon": 77.712296, "tags": {"addr:block": "Tirunelveli Corp", "addr:district": "Tirunelveli", "addr:full": "5B, Behind Hotel Aaryaas, Tirunelveli Junction, Thilak Street", "addr:postcode": "627001", "addr:state": "Tamil Nadu", "amenity": "clinic", "healthcare": "clinic", "name": "Chellam Natarajan Nursing Home", "source": "OpenGovernmentData"}}, {"type": "node", "id": 7249356845, "lat": 8.6770516, "lon": 77.7412301, "tags": {"addr:block": "Palayamkottai", "addr:district": "Tirunelveli", "addr:full": "1/59A, Near Phc,Reddiyarpatti, Reddiyarpatti, Vadabagam Street", "addr:postcode": "627007", "addr:state": "Tamil Nadu", "amenity": "hospital", "name": "J.K.Hospital", "source": "OpenGovernmentData"}}, {"type": "node", "id": 7249356856, "lat": 8.730101, "lon": 77.681362, "tags": {"addr:block": "Tirunelveli Corp", "addr:district": "Tirunelveli", "addr:full": "90/1-A2, Near Uzhavar Sannathi, Tirunelveli Road, Lalugapuram, Tirunelveli Town", "addr:postcode": "627006", "addr:state": "Tamil Nadu", "amenity": "clinic", "healthcare": "clinic", "name": "Jamiaah Nursing Home", "source": "OpenGovernmentData"}}, {"type": "node", "id": 7249356874, "lat": 8.7040917, "lon": 77.735289, "tags": {"addr:block": "Tirunelveli Corp", "addr:city": "Tirunelveli", "addr:district": "Tirunelveli", "addr:full": "38, 7Th St, Perumalpuram, Palayamkottai, Tirunelveli", "addr:postcode": "627007", "addr:state": "Tamil Nadu", "addr:street": "7th Street", "amenity": "clinic", "healthcare": "clinic", "healthcare:speciality": "gynaecology;dentist", "name": "El-Shaddai Nursing Home", "source": "OpenGovernmentData"}}, {"type": "node", "id": 7249356883, "lat": 8.7162149, "lon": 77.7321912, "tags": {"addr:block": "Tirunelveli Corp", "addr:district": "Tirunelveli", "addr:full": "Near Palai Bus Stand, Palayamkottai, Tvm Road", "addr:postcode": "627002", "addr:state": "Tamil Nadu", "amenity": "hospital", "healthcare": "hospital", "name": "Muthamil Hospital", "source": "OpenGovernmentData"}}, {"type": "node", "id": 7249356892, "lat": 8.729866, "lon": 77.71944, "tags": {"addr:block": "Palayamkottai", "addr:district": "Tirunelveli", "addr:full": "Kailash Nagar, Vannarpettai, Tirunelveli", "addr:postcode": "627003", "addr:state": "Tamil Nadu", "amenity": "hospital", "healthcare": "hospital", "name": "Sudharson Platinum Hospitals", "source": "OpenGovernmentData"}}, {"type": "node", "id": 7249356898, "lat": 8.7231595, "lon": 77.6915029, "tags": {"addr:block": "Tirunelveli Corp", "addr:district": "Tirunelveli", "addr:full": "3, Kurukkuthurai Road, Near Arunagiri Theatre, Opposite Ttd Information Center, Tirunelveli Town, Kuruvukulam Road", "addr:postcode": "627006", "addr:state": "Tamil Nadu", "amenity": "hospital", "healthcare": "hospital", "name": "Jeyarathna Hospital", "source": "OpenGovernmentData"}}, {"type": "node", "id": 7249356904, "lat": 8.6735412, "lon": 77.7437318, "tags": {"addr:block": "Palayamkottai", "addr:district": "Tirunelveli", "addr:full": "Ph-312, Panchayat Union Office, Reddiarpatti, Sivanthipatti Road", "addr:postcode": "627007", "addr:state": "Tamil Nadu", "amenity": "hospital", "name": "Government Hospital, Reddiarpatti", "source": "OpenGovernmentData"}}, {"type": "node", "id": 7249356930, "lat": 8.7284606, "lon": 77.7101795, "tags": {"addr:block": "Palayamkottai", "addr:district": "Tirunelveli", "addr:full": "82, Near Poornakala Theatre, Tirunelveli, Kailasapuram Middle Street", "addr:housenumber": "82", "addr:postcode": "627001", "addr:state": "Tamil Nadu", "addr:street": "Kailasapuram Middle Street", "amenity": "hospital", "healthcare": "hospital", "name": "Shifa Hospital", "phone": "9442139292", "source": "OpenGovernmentData"}}, {"type": "node", "id": 7249356935, "lat": 8.7267341, "lon": 77.7388735, "tags": {"addr:block": "Tirunelveli Corp", "addr:district": "Tirunelveli", "addr:full": "NH 7A, Palayamkottai, Tirunelveli", "addr:postcode": "627002", "addr:state": "Tamil Nadu", "amenity": "hospital", "healthcare": "hospital", "name": "Manakaavalam Pillai Government Hospital", "source": "OpenGovernmentData"}}, {"type": "node", "id": 7249356950, "lat": 8.6995388, "lon": 77.7264438, "tags": {"addr:block": "Palayamkottai", "addr:district": "Tirunelveli", "addr:full": "48.H/5, Near New Bus Stand, Palayamkottai, South By Pass Road;#48, H/5, Bye - Pass Road,New Bus Stand View", "addr:postcode": "627005", "addr:state": "Tamil Nadu", "amenity": "hospital", "healthcare": "hospital", "name": "Peace Health Centre", "source": "OpenGovernmentData"}}, {"type": "node", "id": 7249356959, "lat": 8.7220798, "lon": 77.6589633, "tags": {"addr:district": "Tirunelveli", "addr:full": "Tirunelveli, Tamil Nadu", "addr:postcode": "627004", "addr:state": "Tamil Nadu", "amenity": "hospital", "healthcare": "hospital", "name": "Pettai Government Hospital", "source": "OpenGovernmentData"}}, {"type": "node", "id": 7249356963, "lat": 8.705728, "lon": 77.709929, "tags": {"addr:block": "Palayamkottai", "addr:district": "Tirunelveli", "addr:full": "Government Hospital Melapalayam, Near Municipality Office, Melapalayam, Abdhulkalam Asath Road", "addr:postcode": "627005", "addr:state": "Tamil Nadu", "amenity": "hospital", "healthcare": "hospital", "name": "Government Hospital, Melapalayam", "source": "OpenGovernmentData"}}, {"type": "node", "id": 7249356968, "lat": 8.7249129, "lon": 77.7312637, "tags": {"addr:block": "Tirunelveli Corp", "addr:district": "Tirunelveli", "addr:full": "Near Selvi Mahal, Chatram Street, Murugankurichi, Palayamkottai, Tirunelveli Town", "addr:postcode": "627002", "addr:state": "Tamil Nadu", "amenity": "hospital", "healthcare": "hospital", "name": "Joseph Hospital", "source": "OpenGovernmentData"}}, {"type": "node", "id": 7841693890, "lat": 8.663892, "lon": 77.826694, "tags": {"addr:district": "Thoothukudi", "addr:full": "Seydunganallur", "addr:postcode": "628809", "addr:state": "Tamil Nadu", "amenity": "hospital", "name": "J.V. Hospital", "source": "Local Knowledge"}}, {"type": "node", "id": 7841693908, "lat": 8.7154667, "lon": 77.848558, "tags": {"addr:district": "Thoothukudi", "addr:full": "Vallanadu", "addr:postcode": "628252", "addr:state": "Tamil Nadu", "amenity": "hospital", "name": "Surya Hospital", "source": "Local Knowledge"}}, {"type": "node", "id": 7843768406, "lat": 8.785905, "lon": 77.724646, "tags": {"addr:district": "Tirunelveli", "addr:full": "Sankarnagar", "addr:postcode": "627357", "addr:state": "Tamil Nadu", "amenity": "clinic", "healthcare": "clinic", "name": "Saradha Clinic", "opening_hours": "24/7", "source": "Local Knowledge"}}, {"type": "node", "id": 7843768415, "lat": 8.787285, "lon": 77.726385, "tags": {"addr:district": "Tirunelveli", "addr:full": "Sankarnagar", "addr:postcode": "627357", "addr:state": "Tamil Nadu", "amenity": "hospital", "healthcare": "hospital", "name": "Precision Dental Clinic", "source": "Local Knowledge", "wheelchair": "limited"}}, {"type": "node", "id": 7843768418, "lat": 8.8909214, "lon": 77.6510483, "tags": {"addr:district": "Tirunelveli", "addr:full": "Pillaiyarkulam", "addr:postcode": "627201", "addr:state": "Tamil Nadu", "amenity": "hospital", "name": "Myopathy Hospital", "source": "Local Knowledge"}}, {"type": "node", "id": 7843768419, "lat": 8.66824, "lon": 77.665116, "tags": {"addr:district": "Tirunelveli", "addr:full": "Tharuvai, Tirunelveli", "addr:postcode": "627451", "addr:state": "Tamil Nadu", "amenity": "hospital", "healthcare": "hospital", "name": "Vaigarai Homeopathy Hospital and Research Centre", "source": "Local Knowledge"}}, {"type": "node", "id": 7843768421, "lat": 8.8950114, "lon": 77.6761534, "tags": {"addr:district": "Tirunelveli", "addr:full": "Pillaiyarkulam", "addr:postcode": "627201", "addr:state": "Tamil Nadu", "amenity": "hospital", "name": "Government Hospital", "source": "Local Knowledge"}}, {"type": "node", "id": 7843768424, "lat": 8.6623605, "lon": 77.5843025, "tags": {"addr:district": "Tirunelveli", "addr:full": "Pattamadai", "addr:postcode": "627453", "addr:state": "Tamil Nadu", "amenity": "hospital", "healthcare": "hospital", "name": "Swami Sivananda Centenary Charitable Hospital", "source": "Local Knowledge"}}, {"type": "node", "id": 7843768425, "lat": 8.81799, "lon": 77.659295, "tags": {"addr:district": "Tirunelveli", "addr:full": "Thenkalam Road, Venkalapottal", "addr:postcode": "627201", "addr:state": "Tamil Nadu", "amenity": "hospital", "name": "Saro Hospital", "source": "Local Knowledge"}}, {"type": "node", "id": 7843768427, "lat": 8.726781, "lon": 77.666446, "tags": {"addr:district": "Tirunelveli", "addr:full": "Vaniga Vaisiyer, Tirunelveli", "addr:postcode": "627004", "addr:state": "Tamil Nadu", "amenity": "hospital", "healthcare": "hospital", "name": "Raaja Hospital", "source": "Local Knowledge"}}, {"type": "node", "id": 7843768428, "lat": 8.7220514, "lon": 77.6586702, "tags": {"addr:district": "Tirunelveli", "addr:full": "Tirunelveli, Pettai", "addr:postcode": "627004", "addr:state": "Tamil Nadu", "amenity": "clinic", "healthcare": "clinic", "name": "Dr. P Arumugam Clinic", "source": "Local Knowledge"}}, {"type": "node", "id": 7843768434, "lat": 8.783733, "lon": 77.723217, "tags": {"addr:district": "Tirunelveli", "addr:full": "Sankar Nagar, Tirunelveli", "addr:postcode": "627357", "addr:state": "Tamil Nadu", "amenity": "hospital", "healthcare": "hospital", "name": "Sumu Priya Hospital", "source": "Local Knowledge", "wheelchair": "yes"}}, {"type": "node", "id": 7843768435, "lat": 8.78517, "lon": 77.7265479, "tags": {"addr:district": "Tirunelveli", "addr:full": "Sankarnagar", "addr:postcode": "627357", "addr:state": "Tamil Nadu", "amenity": "clinic", "healthcare": "clinic", "name": "Ram Swarna Clinic", "source": "Local Knowledge"}}, {"type": "node", "id": 7843768438, "lat": 8.6622962, "lon": 77.5844495, "tags": {"addr:district": "Tirunelveli", "addr:full": "Pattamadai", "addr:postcode": "627453", "addr:state": "Tamil Nadu", "amenity": "clinic", "healthcare": "clinic", "name": "Aravind Vision Centre", "source": "Local Knowledge"}}, {"type": "node", "id": 7843768446, "lat": 8.787162, "lon": 77.726567, "tags": {"addr:district": "Tirunelveli", "addr:full": "Sankarnagar", "addr:postcode": "627357", "addr:state": "Tamil Nadu", "amenity": "hospital", "healthcare": "hospital", "name": "ESI Hospital", "operator": "Employees' State Insurance", "operator:short": "ESI", "operator:wikidata": "Q3595726", "operator:wikipedia": "hi:\u0915\u0930\u094d\u092e\u091a\u093e\u0930\u0940 \u0930\u093e\u091c\u094d\u200d\u092f \u092c\u0940\u092e\u093e \u0928\u093f\u0917\u092e", "source": "Local Knowledge"}}, {"type": "node", "id": 7843768448, "lat": 8.670143, "lon": 77.5858102, "tags": {"addr:district": "Tirunelveli", "addr:full": "Pattamadai Road, Pattamadai", "addr:postcode": "627453", "addr:state": "Tamil Nadu", "amenity": "clinic", "healthcare": "clinic", "name": "Healthy World Physiotherapy Clinic", "source": "Local Knowledge"}}, {"type": "node", "id": 7843768452, "lat": 8.762617, "lon": 77.708793, "tags": {"addr:district": "Tirunelveli", "addr:full": "Tirunelveli", "addr:postcode": "627358", "addr:state": "Tamil Nadu", "amenity": "clinic", "healthcare": "clinic", "name": "Ram Swarna Clinic", "source": "Local Knowledge"}}, {"type": "node", "id": 7843768453, "lat": 8.815422, "lon": 77.680813, "tags": {"addr:district": "Tirunelveli", "addr:full": "Sankarnagar", "addr:postcode": "627357", "addr:state": "Tamil Nadu", "amenity": "hospital", "name": "Rajathiran Hospital", "source": "Local Knowledge"}}, {"type": "node", "id": 7843768467, "lat": 8.7234105, "lon": 77.6620741, "tags": {"addr:district": "Tirunelveli", "addr:full": "Pettai, Tirunelveli", "addr:postcode": "627004", "addr:state": "Tamil Nadu", "amenity": "hospital", "healthcare": "hospital", "name": "Nellai Test Tube Baby Hospital", "source": "Local Knowledge"}}, {"type": "node", "id": 7843768470, "lat": 8.722522, "lon": 77.659294, "tags": {"addr:district": "Tirunelveli", "addr:full": "Tirunelveli", "addr:postcode": "627004", "addr:state": "Tamil Nadu", "amenity": "hospital", "healthcare": "hospital", "name": "Kaithe Millath Hospital", "source": "Local Knowledge"}}, {"type": "node", "id": 7843768473, "lat": 8.669492, "lon": 77.66992, "tags": {"addr:district": "Tirunelveli", "addr:full": "Tharuvai", "addr:postcode": "627451", "addr:state": "Tamil Nadu", "amenity": "clinic", "healthcare": "clinic", "name": "JR Rehabilitation Centre", "source": "Local Knowledge"}}, {"type": "node", "id": 7843768476, "lat": 8.6694785, "lon": 77.6692658, "tags": {"addr:district": "Tirunelveli", "addr:full": "Tirunelveli", "addr:postcode": "627451", "addr:state": "Tamil Nadu", "amenity": "hospital", "healthcare": "hospital", "name": "Vidivelli Hospitals", "source": "Local Knowledge"}}, {"type": "node", "id": 7843768479, "lat": 8.804653, "lon": 77.736598, "tags": {"addr:district": "Tirunelveli", "addr:full": "Sankarnagar", "addr:postcode": "627357", "addr:state": "Tamil Nadu", "amenity": "hospital", "healthcare": "hospital", "name": "Sankar Hospital", "source": "Local Knowledge"}}, {"type": "node", "id": 7843768484, "lat": 8.671871, "lon": 77.58752, "tags": {"addr:district": "Tirunelveli", "addr:full": "Pattamadai", "addr:postcode": "627453", "addr:state": "Tamil Nadu", "amenity": "hospital", "healthcare": "hospital", "name": "Government Hospital", "source": "Local Knowledge"}}, {"type": "node", "id": 7843768487, "lat": 8.7252341, "lon": 77.6624868, "tags": {"addr:district": "Tirunelveli", "addr:full": "Tirunelveli", "addr:postcode": "627004", "addr:state": "Tamil Nadu", "amenity": "doctors", "healthcare": "doctor", "name": "Dr. Salahuddin", "operational_status": "non operational", "source": "Local Knowledge"}}, {"type": "node", "id": 7843768488, "lat": 8.671779, "lon": 77.615767, "tags": {"addr:district": "Tirunelveli", "addr:full": "Melacheval", "addr:postcode": "627452", "addr:state": "Tamil Nadu", "amenity": "doctors", "name": "Dr. Seenevasan", "source": "Local Knowledge"}}, {"type": "node", "id": 7843768489, "lat": 8.725932, "lon": 77.663712, "tags": {"addr:district": "Tirunelveli", "addr:full": "Tirunelveli", "addr:postcode": "627004", "addr:state": "Tamil Nadu", "amenity": "hospital", "healthcare": "hospital", "name": "Thilaks Hospital", "source": "Local Knowledge"}}, {"type": "node", "id": 7843768490, "lat": 8.724189, "lon": 77.663674, "tags": {"addr:district": "Tirunelveli", "addr:full": "Tirunelveli", "addr:postcode": "627004", "addr:state": "Tamil Nadu", "amenity": "hospital", "healthcare": "hospital", "name": "IRK Siddha Hospital", "source": "Local Knowledge"}}, {"type": "node", "id": 7844921867, "lat": 8.58171, "lon": 77.587209, "tags": {"addr:district": "Tirunelveli", "addr:full": "Idaiyankulam", "addr:postcode": "627502", "addr:state": "Tamil Nadu", "amenity": "hospital", "name": "Aysha Hospital", "source": "Local Knowledge"}}, {"type": "node", "id": 7844921871, "lat": 8.5969824, "lon": 77.5775633, "tags": {"addr:district": "Tirunelveli", "addr:full": "Vadakku Idaiyan Kulam", "addr:postcode": "627502", "addr:state": "Tamil Nadu", "amenity": "doctors", "name": "Dr. A.Gnanasekarapandian", "source": "Local Knowledge"}}, {"type": "node", "id": 7844921883, "lat": 8.5973872, "lon": 77.7120556, "tags": {"addr:district": "Tirunelveli", "addr:full": "Maruthakulam", "addr:postcode": "627151", "addr:state": "Tamil Nadu", "amenity": "hospital", "name": "Luke Hospital", "source": "Local Knowledge"}}, {"type": "node", "id": 7844921898, "lat": 8.608277, "lon": 77.577132, "tags": {"addr:district": "Tirunelveli", "addr:full": "Tirunelveli", "addr:postcode": "627414", "addr:state": "Tamil Nadu", "amenity": "hospital", "name": "Government Hospital", "source": "Local Knowledge"}}, {"type": "node", "id": 7844921921, "lat": 8.6289855, "lon": 77.6975614, "tags": {"addr:district": "Tirunelveli", "addr:full": "Ponnakudi", "addr:postcode": "627151", "addr:state": "Tamil Nadu", "amenity": "hospital", "name": "SCAD Hospital", "source": "Local Knowledge"}}, {"type": "node", "id": 7847045736, "lat": 8.7049877, "lon": 77.7522769, "tags": {"addr:district": "Tirunelveli", "addr:full": "Maharaja Nagar, Tirunelveli", "addr:postcode": "627011", "addr:state": "Tamil Nadu", "amenity": "hospital", "healthcare": "hospital", "name": "Sri Kala Ayurvedic and Siddha Hospital", "source": "Local Knowledge"}}, {"type": "node", "id": 7847045737, "lat": 8.7137097, "lon": 77.783159, "tags": {"addr:district": "Tirunelveli", "addr:postcode": "627011", "addr:state": "Tamil Nadu", "amenity": "clinic", "healthcare": "clinic", "name": "Krishna Homeopathy Clinics", "source": "Local Knowledge"}}, {"type": "node", "id": 7847045738, "lat": 8.7058849, "lon": 77.7513675, "tags": {"addr:district": "Tirunelveli", "addr:full": "Maharaja Nagar, Tirunelveli", "addr:postcode": "627011", "addr:state": "Tamil Nadu", "amenity": "hospital", "healthcare": "hospital", "name": "Maya Hospital", "source": "Local Knowledge"}}, {"type": "node", "id": 7847045739, "lat": 8.7259399, "lon": 77.7055643, "tags": {"addr:district": "Tirunelveli", "addr:full": "Tirunelveli", "addr:postcode": "627001", "addr:state": "Tamil Nadu", "amenity": "hospital", "healthcare": "hospital", "name": "RSP Hospital", "source": "Local Knowledge"}}, {"type": "node", "id": 7847045740, "lat": 8.6992812, "lon": 77.7327907, "tags": {"addr:district": "Tirunelveli", "addr:full": "Vasantha Nager, Tirunelveli", "addr:postcode": "627007", "addr:state": "Tamil Nadu", "amenity": "hospital", "healthcare": "hospital", "name": "Kumar Hospital", "source": "Local Knowledge"}}, {"type": "node", "id": 7847045741, "lat": 8.7216324, "lon": 77.7538382, "tags": {"addr:district": "Tirunelveli", "addr:full": "Kamaraj Nagar, Tirunelveli", "addr:postcode": "627002", "addr:state": "Tamil Nadu", "amenity": "clinic", "healthcare": "clinic", "name": "Subuhani Heart Centre", "source": "Local Knowledge"}}, {"type": "node", "id": 7847045742, "lat": 8.699246, "lon": 77.714533, "tags": {"addr:district": "Tirunelveli", "addr:full": "Raja Nagar, Melapalayam, Tirunelveli", "addr:postcode": "627005", "addr:state": "Tamil Nadu", "amenity": "hospital", "healthcare": "hospital", "name": "Jayakumar Hospital", "source": "Local Knowledge"}}, {"type": "node", "id": 7847045744, "lat": 8.7274381, "lon": 77.7081868, "tags": {"addr:district": "Tirunelveli", "addr:postcode": "627001", "addr:state": "Tamil Nadu", "amenity": "hospital", "healthcare": "hospital", "name": "Sri Devi Hospital", "source": "Local Knowledge"}}, {"type": "node", "id": 7847045747, "lat": 8.713907, "lon": 77.760271, "tags": {"addr:district": "Tirunelveli", "addr:full": "Maharaja Nagar, Tirunelveli", "addr:postcode": "627011", "addr:state": "Tamil Nadu", "amenity": "hospital", "healthcare": "hospital", "name": "Tirunelveli Multi-Speciality Hospital", "source": "Local Knowledge"}}, {"type": "node", "id": 7847045748, "lat": 8.724715, "lon": 77.6866393, "tags": {"addr:district": "Tirunelveli", "addr:full": "Tirunelveli", "addr:postcode": "627006", "addr:state": "Tamil Nadu", "amenity": "hospital", "healthcare": "hospital", "name": "Sri Guru Hospital", "source": "Local Knowledge"}}, {"type": "node", "id": 7847045749, "lat": 8.7125221, "lon": 77.7478902, "tags": {"addr:district": "Tirunelveli", "addr:full": "Palayamkottai, Tirunelveli", "addr:postcode": "627007", "addr:state": "Tamil Nadu", "amenity": "hospital", "healthcare": "hospital", "name": "Government Hospital", "source": "Local Knowledge"}}, {"type": "node", "id": 7847045752, "lat": 8.7320389, "lon": 77.7494099, "tags": {"addr:district": "Tirunelveli", "addr:full": "Shanthi Nagar, Palayamkottai, Tirunelveli", "addr:postcode": "627002", "addr:state": "Tamil Nadu", "amenity": "hospital", "healthcare": "hospital", "name": "Jeni Hospital", "source": "Local Knowledge"}}, {"type": "node", "id": 7847045753, "lat": 8.7301989, "lon": 77.6811267, "tags": {"addr:district": "Tirunelveli", "addr:full": "Lalugapuram, Nellai Nagaram, Tirunelveli", "addr:postcode": "627006", "addr:state": "Tamil Nadu", "amenity": "hospital", "healthcare": "hospital", "name": "Akbar Hospital", "source": "Local Knowledge"}}, {"type": "node", "id": 7847045754, "lat": 8.7270657, "lon": 77.7480305, "tags": {"addr:district": "Tirunelveli", "addr:full": "Shakthi Nagar, Palayamkottai, Tirunelveli", "addr:postcode": "627002", "addr:state": "Tamil Nadu", "amenity": "clinic", "healthcare": "clinic", "name": "Parvathi Physiotherapy Clinic", "source": "Local Knowledge"}}, {"type": "node", "id": 7847045755, "lat": 8.726517, "lon": 77.673099, "tags": {"addr:district": "Tirunelveli", "addr:full": "Kodeeswaran Nagar, Tirunelveli", "addr:postcode": "627006", "addr:state": "Tamil Nadu", "amenity": "hospital", "healthcare": "hospital", "name": "Sathya Hospital", "source": "Local Knowledge"}}, {"type": "node", "id": 7847045756, "lat": 8.6881316, "lon": 77.7256395, "tags": {"addr:district": "Tirunelveli", "addr:full": "Marshal Nagar, Tirunelveli", "addr:postcode": "627007", "addr:state": "Tamil Nadu", "amenity": "clinic", "healthcare": "clinic", "name": "ECHS Polyclinic", "source": "Local Knowledge"}}, {"type": "node", "id": 7847045759, "lat": 8.6965281, "lon": 77.7121846, "tags": {"addr:district": "Tirunelveli", "addr:full": "Hameempuram, Raja Nagar, Tirunelveli", "addr:postcode": "627005", "addr:state": "Tamil Nadu", "amenity": "hospital", "healthcare": "hospital", "name": "Sree Vijaya Children's Hospital", "source": "Local Knowledge"}}, {"type": "node", "id": 7847045760, "lat": 8.732999, "lon": 77.7134851, "tags": {"addr:district": "Tirunelveli", "addr:full": "Sindupoonduraii, Tirunelveli", "addr:postcode": "627001", "addr:state": "Tamil Nadu", "amenity": "clinic", "healthcare": "clinic", "name": "M.G. Clinic", "source": "Local Knowledge"}}, {"type": "node", "id": 7847045761, "lat": 8.731177, "lon": 77.702675, "tags": {"addr:district": "Tirunelveli", "addr:full": "Sripuram, Tirunelveli", "addr:postcode": "627001", "addr:state": "Tamil Nadu", "amenity": "hospital", "healthcare": "hospital", "name": "K.G. Hospital", "source": "Local Knowledge"}}, {"type": "node", "id": 7847045762, "lat": 8.7282209, "lon": 77.6902836, "tags": {"addr:district": "Tirunelveli", "addr:full": "Tirunelveli", "addr:postcode": "627006", "addr:state": "Tamil Nadu", "amenity": "hospital", "healthcare": "hospital", "name": "Anam Hospital", "source": "Local Knowledge"}}, {"type": "node", "id": 7847045763, "lat": 8.7083213, "lon": 77.7699316, "tags": {"addr:district": "Tirunelveli", "addr:full": "V.M.Chatram", "addr:postcode": "627011", "addr:state": "Tamil Nadu", "amenity": "hospital", "healthcare": "hospital", "name": "BMK Siddha Hospital", "source": "Local Knowledge"}}, {"type": "node", "id": 7847045764, "lat": 8.7239005, "lon": 77.7427932, "tags": {"addr:district": "Tirunelveli", "addr:full": "Palayamkottai, Tirunelveli", "addr:postcode": "627002", "addr:state": "Tamil Nadu", "amenity": "clinic", "healthcare": "clinic", "name": "Karunya Health Centre", "source": "Local Knowledge"}}, {"type": "node", "id": 7847045765, "lat": 8.724657, "lon": 77.686862, "tags": {"addr:district": "Tirunelveli", "addr:full": "Tirunelveli Town, Tirunelveli", "addr:postcode": "627006", "addr:state": "Tamil Nadu", "amenity": "clinic", "healthcare": "clinic", "name": "Jamuna Clinic", "source": "Local Knowledge"}}, {"type": "node", "id": 7847045766, "lat": 8.7136233, "lon": 77.7578061, "tags": {"addr:district": "Tirunelveli", "addr:full": "Palayamkottai, Tirunelveli", "addr:postcode": "627011", "addr:state": "Tamil Nadu", "amenity": "hospital", "healthcare": "hospital"}}, {"type": "node", "id": 7847045767, "lat": 8.7215926, "lon": 77.7573834, "tags": {"addr:district": "Tirunelveli", "addr:full": "Kamaraj Nagar, Tirunelveli", "addr:postcode": "627002", "addr:state": "Tamil Nadu", "amenity": "hospital", "healthcare": "hospital", "name": "Orange Hospital", "source": "Local Knowledge"}}, {"type": "node", "id": 7847045768, "lat": 8.7246227, "lon": 77.7454165, "tags": {"addr:district": "Tirunelveli", "addr:full": "Shakthi Nagar, Palayamkottai, Tirunelveli", "addr:postcode": "627002", "addr:state": "Tamil Nadu", "amenity": "clinic", "healthcare": "clinic", "name": "Rafael Clinic", "source": "Local Knowledge"}}, {"type": "node", "id": 7847045769, "lat": 8.7226721, "lon": 77.7409117, "tags": {"addr:district": "Tirunelveli", "addr:full": "Palayamkottai, Tirunelveli", "addr:postcode": "627002", "addr:state": "Tamil Nadu", "amenity": "hospital", "healthcare": "hospital", "name": "Mother Hospital", "source": "Local Knowledge"}}, {"type": "node", "id": 7847045770, "lat": 8.6988269, "lon": 77.7102825, "tags": {"addr:district": "Tirunelveli", "addr:full": "Melapalayam, Tirunelveli", "addr:postcode": "627005", "addr:state": "Tamil Nadu", "amenity": "hospital", "healthcare": "hospital", "name": "St. Paull's Hospital", "source": "Local Knowledge"}}, {"type": "node", "id": 7847045771, "lat": 8.7050571, "lon": 77.7584201, "tags": {"addr:district": "Tirunelveli", "addr:full": "Velavar Colony, Maharaja Nagar, Tirunelveli", "addr:postcode": "627011", "addr:state": "Tamil Nadu", "amenity": "hospital", "healthcare": "hospital", "name": "Venkateswara Hospital", "source": "Local Knowledge"}}, {"type": "node", "id": 7847045772, "lat": 8.725328, "lon": 77.707601, "tags": {"addr:district": "Tirunelveli", "addr:full": "Meenakshipuram, Tirunelveli", "addr:postcode": "627001", "addr:state": "Tamil Nadu", "amenity": "hospital", "healthcare": "hospital", "name": "Nagarpura Aramba Sugathara Nilayam", "source": "Local Knowledge"}}, {"type": "node", "id": 7847045773, "lat": 8.6955281, "lon": 77.7159246, "tags": {"addr:district": "Tirunelveli", "addr:full": "Raja Nagar, Melapalayam, Tirunelveli", "addr:postcode": "627005", "addr:state": "Tamil Nadu", "amenity": "hospital", "healthcare": "hospital", "name": "Crescent Hospital", "source": "Local Knowledge"}}, {"type": "node", "id": 7847045774, "lat": 8.7157091, "lon": 77.7618563, "tags": {"addr:district": "Tirunelveli", "addr:full": "Palayamkottai, Tirunelveli", "addr:postcode": "627002", "addr:state": "Tamil Nadu", "amenity": "hospital", "healthcare": "hospital", "name": "Dr. Allapitchai Hospital", "source": "Local Knowledge"}}, {"type": "node", "id": 7847045775, "lat": 8.703941, "lon": 77.730072, "tags": {"addr:district": "Tirunelveli", "addr:full": "Perumalpuram, Vasantha Nagar, Tirunelveli", "addr:postcode": "627007", "addr:state": "Tamil Nadu", "amenity": "hospital", "healthcare": "hospital", "name": "Iswarya Fertility Hospital", "source": "Local Knowledge"}}, {"type": "node", "id": 7847045776, "lat": 8.700556, "lon": 77.725985, "tags": {"addr:district": "Tirunelveli", "addr:full": "Vasanth Nagar, Tirunelveli", "addr:postcode": "627005", "addr:state": "Tamil Nadu", "amenity": "hospital", "healthcare": "hospital", "name": "Diawin Multi Speciality Siddha Hospital", "source": "Local Knowledge"}}, {"type": "node", "id": 7847045777, "lat": 8.7184475, "lon": 77.7411363, "tags": {"addr:district": "Tirunelveli", "addr:full": "Palayamkottai, Tirunelveli", "addr:postcode": "627007", "addr:state": "Tamil Nadu", "amenity": "hospital", "healthcare": "hospital", "name": "Narayana Heart Centre", "source": "Local Knowledge"}}, {"type": "node", "id": 7847045778, "lat": 8.715427, "lon": 77.770537, "tags": {"addr:district": "Tirunelveli", "addr:full": "KTC Nagar, Tirunelveli", "addr:postcode": "627011", "addr:state": "Tamil Nadu", "amenity": "clinic", "healthcare": "clinic", "name": "Shalom Clinic", "source": "Local Knowledge"}}, {"type": "node", "id": 7847045781, "lat": 8.730492, "lon": 77.748318, "tags": {"addr:district": "Tirunelveli", "addr:full": "Shakthi Nagar, Palayamkottai, Tirunelveli", "addr:postcode": "627002", "addr:state": "Tamil Nadu", "amenity": "clinic", "healthcare": "clinic", "name": "Kavitha Clinic", "source": "Local Knowledge"}}, {"type": "node", "id": 7847045783, "lat": 8.7261442, "lon": 77.7088774, "tags": {"addr:district": "Tirunelveli", "addr:full": "Meenakshipuram, Tirunelveli", "addr:postcode": "627006", "addr:state": "Tamil Nadu", "amenity": "hospital", "healthcare": "hospital", "name": "Ganesh Sankar Hospital", "source": "Local Knowledge"}}, {"type": "node", "id": 7847045784, "lat": 8.7241481, "lon": 77.7467411, "tags": {"addr:district": "Tirunelveli", "addr:full": "Palayamkottai, Tirunelveli", "addr:postcode": "627002", "addr:state": "Tamil Nadu", "amenity": "clinic", "healthcare": "clinic", "name": "Jazbah Clinic", "source": "Local Knowledge"}}, {"type": "node", "id": 7847045785, "lat": 8.7278984, "lon": 77.7103496, "tags": {"addr:district": "Tirunelveli", "addr:full": "Meenakshipuram", "addr:postcode": "627001", "addr:state": "Tamil Nadu", "amenity": "hospital", "healthcare": "hospital", "name": "Shifa Eye Hospital", "source": "Local Knowledge"}}, {"type": "node", "id": 7847045786, "lat": 8.7282846, "lon": 77.6831491, "tags": {"addr:district": "Tirunelveli", "addr:full": "Tirunelveli", "addr:postcode": "627006", "addr:state": "Tamil Nadu", "amenity": "clinic", "healthcare": "clinic", "name": "Suriya Clinic", "source": "Local Knowledge"}}, {"type": "node", "id": 7847045787, "lat": 8.7108953, "lon": 77.726631, "tags": {"addr:district": "Tirunelveli", "addr:full": "Kulavanigarpuram, Tirunelveli", "addr:postcode": "627002", "addr:state": "Tamil Nadu", "amenity": "hospital", "healthcare": "hospital", "name": "Muthu Hospital", "source": "Local Knowledge"}}, {"type": "node", "id": 7847045788, "lat": 8.7233299, "lon": 77.6832293, "tags": {"addr:district": "Tirunelveli", "addr:full": "Thirunagar, Tirunelveli", "addr:postcode": "627002", "addr:state": "Tamil Nadu", "amenity": "doctors", "healthcare": "doctor", "name": "Dr. S. Vinoth Kumar", "source": "Local Knowledge"}}, {"type": "node", "id": 7847045790, "lat": 8.7313103, "lon": 77.6820219, "tags": {"addr:district": "Tirunelveli", "addr:full": "Lalugapuram, Nellai Nagaram, Tirunelveli", "addr:postcode": "627006", "addr:state": "Tamil Nadu", "amenity": "hospital", "healthcare": "hospital", "name": "Ramasamy Memorial Government Hospital", "source": "Local Knowledge"}}, {"type": "node", "id": 7847045791, "lat": 8.7187415, "lon": 77.7429191, "tags": {"addr:district": "Tirunelveli", "addr:full": "Palayamkottai, Tirunelveli", "addr:postcode": "627007", "addr:state": "Tamil Nadu", "amenity": "clinic", "healthcare": "clinic", "name": "Dr.Godson, Rehoboth Psychiatry Clinic", "source": "Local Knowledge"}}, {"type": "node", "id": 7847045792, "lat": 8.719115, "lon": 77.77135, "tags": {"addr:district": "Tirunelveli", "addr:full": "KTC Nagar, Tirunelveli", "addr:postcode": "627011", "addr:state": "Tamil Nadu", "amenity": "hospital", "healthcare": "hospital", "name": "Gokul Hospital", "source": "Local Knowledge"}}, {"type": "node", "id": 7847045793, "lat": 8.7290631, "lon": 77.7004975, "tags": {"addr:district": "Tirunelveli", "addr:full": "Tirunelveli", "addr:postcode": "627117", "addr:state": "Tamil Nadu", "amenity": "hospital", "healthcare": "hospital", "name": "Prem Hospital", "source": "Local Knowledge"}}, {"type": "node", "id": 7847045794, "lat": 8.701241, "lon": 77.7296439, "tags": {"addr:district": "Tirunelveli", "addr:full": "Tirunelveli", "addr:postcode": "627007", "addr:state": "Tamil Nadu", "amenity": "hospital", "healthcare": "hospital", "name": "Rhock Hospital", "source": "Local Knowledge"}}, {"type": "node", "id": 7847045795, "lat": 8.6994124, "lon": 77.7254955, "tags": {"addr:district": "Tirunelveli", "addr:full": "Tirunelveli", "addr:postcode": "627005", "addr:state": "Tamil Nadu", "amenity": "clinic", "healthcare": "clinic", "name": "Almaa Siddha Care Clinic", "source": "Local Knowledge"}}, {"type": "node", "id": 7847045796, "lat": 8.7047779, "lon": 77.737778, "tags": {"addr:district": "Tirunelveli", "addr:full": "Perumalpuram, Vasantha Nager, Tirunelveli", "addr:postcode": "627007", "addr:state": "Tamil Nadu", "amenity": "hospital", "healthcare": "hospital", "name": "Annai Indira Gandhi Memorial Trust", "source": "Local Knowledge"}}, {"type": "node", "id": 7847045797, "lat": 8.719588, "lon": 77.758575, "tags": {"addr:district": "Tirunelveli", "addr:full": "Rahmath Nagar, Palayamkottai, Tirunelveli", "addr:postcode": "627002", "addr:state": "Tamil Nadu", "amenity": "hospital", "healthcare": "hospital", "name": "Sri Vishnupriya Multi-Speciality Hospital", "source": "Local Knowledge"}}, {"type": "node", "id": 7847045798, "lat": 8.7029892, "lon": 77.7138648, "tags": {"addr:district": "Tirunelveli", "addr:full": "Veeramanikapuram, Melapalayam, Tirunelveli", "addr:postcode": "627005", "addr:state": "Tamil Nadu", "amenity": "clinic", "healthcare": "clinic", "name": "Velavan ENT Clinic", "source": "Local Knowledge"}}, {"type": "node", "id": 7847045799, "lat": 8.7365637, "lon": 77.711893, "tags": {"addr:district": "Tirunelveli", "addr:postcode": "627001", "addr:state": "Tamil Nadu", "amenity": "hospital", "healthcare": "hospital", "name": "RJR Herbal Hospitals", "source": "Local Knowledge"}}, {"type": "node", "id": 7847045800, "lat": 8.717308, "lon": 77.72032, "tags": {"addr:district": "Tirunelveli", "addr:full": "Kokkirakulam, Tirunelveli", "addr:postcode": "627009", "addr:state": "Tamil Nadu", "amenity": "hospital", "healthcare": "hospital", "name": "Rathinam Hospital", "source": "Local Knowledge"}}, {"type": "node", "id": 7847045801, "lat": 8.704319, "lon": 77.730317, "tags": {"addr:district": "Tirunelveli", "addr:full": "Perumalpuram, Tirunelveli", "addr:postcode": "627007", "addr:state": "Tamil Nadu", "amenity": "hospital", "healthcare": "hospital", "name": "ARC Fertility Hospital", "source": "Local Knowledge"}}, {"type": "node", "id": 7847045802, "lat": 8.7192645, "lon": 77.7645363, "tags": {"addr:district": "Tirunelveli", "addr:full": "Tirunelveli", "addr:postcode": "627002", "addr:state": "Tamil Nadu", "amenity": "hospital", "healthcare": "hospital", "name": "Chella Suriya Hospital", "source": "Local Knowledge"}}, {"type": "node", "id": 7847045803, "lat": 8.7153078, "lon": 77.7518208, "tags": {"addr:district": "Tirunelveli", "addr:full": "Vannarpettai, Tirunelveli", "addr:postcode": "627003", "addr:state": "Tamil Nadu", "amenity": "clinic", "healthcare": "clinic", "name": "Asokam Siddha Care", "source": "Local Knowledge"}}, {"type": "node", "id": 7847111677, "lat": 8.7257201, "lon": 77.7175482, "tags": {"addr:district": "Tirunelveli", "addr:full": "Kokkirakulam, Tirunelveli", "addr:postcode": "627009", "addr:state": "Tamil Nadu", "amenity": "hospital", "healthcare": "hospital", "name": "Ortho Cure Hospital", "source": "Local Knowledge"}}, {"type": "node", "id": 7847111678, "lat": 8.732466, "lon": 77.719815, "tags": {"addr:district": "Tirunelveli", "addr:full": "Vannarpettai, Tirunelveli", "addr:postcode": "627003", "addr:state": "Tamil Nadu", "amenity": "clinic", "healthcare": "clinic", "name": "Gold Child & Chest Clinic", "source": "Local Knowledge"}}, {"type": "node", "id": 7847111680, "lat": 8.7273171, "lon": 77.7358714, "tags": {"addr:district": "Tirunelveli", "addr:full": "Palayamkottai, Tirunelveli", "addr:postcode": "627002", "addr:state": "Tamil Nadu", "amenity": "clinic", "healthcare": "clinic", "name": "American Clinic", "source": "Local Knowledge"}}, {"type": "node", "id": 7847111682, "lat": 8.725856, "lon": 77.7311417, "tags": {"addr:district": "Tirunelveli", "addr:full": "Murugankurichi, Thimmarajapuram, Tirunelveli", "addr:postcode": "627002", "addr:state": "Tamil Nadu", "amenity": "clinic", "healthcare": "clinic", "name": "Sri Vijayalakshmi Homeo Clinic", "source": "Local Knowledge"}}, {"type": "node", "id": 7847111683, "lat": 8.7200075, "lon": 77.7319875, "tags": {"addr:district": "Tirunelveli", "addr:full": "Palayamkottai, Tirunelveli", "addr:postcode": "627002", "addr:state": "Tamil Nadu", "amenity": "clinic", "healthcare": "clinic", "name": "Spine Physiotherapy", "source": "Local Knowledge"}}, {"type": "node", "id": 7847111684, "lat": 8.711991, "lon": 77.73179, "tags": {"addr:district": "Tirunelveli", "addr:full": "Kattnayakan, Palayamkottai, Tirunelveli", "addr:postcode": "627007", "addr:state": "Tamil Nadu", "amenity": "hospital", "healthcare": "hospital", "name": "Seed Trust Siddha Hospital", "source": "Local Knowledge"}}, {"type": "node", "id": 7847111686, "lat": 8.7291262, "lon": 77.7205343, "tags": {"addr:district": "Tirunelveli", "addr:full": "Kailash Nagar, Vannarpettai, Tirunelveli", "addr:postcode": "627003", "addr:state": "Tamil Nadu", "amenity": "hospital", "healthcare": "hospital", "name": "ESI Hospital", "operator": "Employees' State Insurance", "operator:short": "ESI", "operator:wikidata": "Q3595726", "operator:wikipedia": "hi:\u0915\u0930\u094d\u092e\u091a\u093e\u0930\u0940 \u0930\u093e\u091c\u094d\u200d\u092f \u092c\u0940\u092e\u093e \u0928\u093f\u0917\u092e", "source": "Local Knowledge"}}, {"type": "node", "id": 7847111687, "lat": 8.7258706, "lon": 77.7357267, "tags": {"addr:district": "Tirunelveli", "addr:full": "Palayamkottai, Tirunelveli", "addr:postcode": "627002", "addr:state": "Tamil Nadu", "amenity": "clinic", "healthcare": "clinic", "name": "M.S.P. Clinic", "source": "Local Knowledge"}}, {"type": "node", "id": 7847111689, "lat": 8.7189244, "lon": 77.7327598, "tags": {"addr:district": "Tirunelveli", "addr:full": "Palayamkottai, Tirunelveli", "addr:postcode": "627002", "addr:state": "Tamil Nadu", "amenity": "clinic", "healthcare": "clinic", "name": "Sai Ortho Centre", "source": "Local Knowledge"}}, {"type": "node", "id": 7847111690, "lat": 8.7461324, "lon": 77.7028142, "tags": {"addr:district": "Tirunelveli", "addr:full": "Azhagu Muthu Nagar, Tirunelveli", "addr:postcode": "627358", "addr:state": "Tamil Nadu", "amenity": "hospital", "healthcare": "hospital", "name": "Adam Ali Hospital", "source": "Local Knowledge"}}, {"type": "node", "id": 7847111691, "lat": 8.7441887, "lon": 77.7044246, "tags": {"addr:district": "Tirunelveli", "addr:full": "Thachanallur, Tirunelveli", "addr:postcode": "627001", "addr:state": "Tamil Nadu", "amenity": "hospital", "healthcare": "hospital", "name": "Syed Hospital", "source": "Local Knowledge"}}, {"type": "node", "id": 7847111692, "lat": 8.7187199, "lon": 77.732946, "tags": {"addr:district": "Tirunelveli", "addr:full": "Palayamkottai, Tirunelveli", "addr:postcode": "627002", "addr:state": "Tamil Nadu", "amenity": "hospital", "healthcare": "hospital", "name": "Jai Ayush Siddha Hospital", "source": "Local Knowledge"}}, {"type": "node", "id": 7847111693, "lat": 8.7190074, "lon": 77.7327344, "tags": {"addr:district": "Tirunelveli", "addr:full": "Palayamkottai, Tirunelveli", "addr:postcode": "627002", "addr:state": "Tamil Nadu", "amenity": "clinic", "healthcare": "clinic", "name": "The Royal Chest Clinic", "source": "Local Knowledge"}}, {"type": "node", "id": 7847111694, "lat": 8.72041, "lon": 77.735581, "tags": {"addr:district": "Tirunelveli", "addr:full": "Palayamkottai, Tirunelveli", "addr:postcode": "627002", "addr:state": "Tamil Nadu", "amenity": "hospital", "healthcare": "hospital", "name": "Ramabhai Ponnudurai Hospital", "source": "Local Knowledge"}}, {"type": "node", "id": 7847111695, "lat": 8.7294097, "lon": 77.7184298, "tags": {"addr:district": "Tirunelveli", "addr:full": "Kailash Nagar, Vannarpettai, Tirunelveli", "addr:postcode": "627003", "addr:state": "Tamil Nadu", "amenity": "hospital", "healthcare": "hospital", "name": "Dr. Velayudhan Pillai Hospital", "source": "Local Knowledge"}}, {"type": "node", "id": 7847111696, "lat": 8.724355, "lon": 77.7313782, "tags": {"addr:district": "Tirunelveli", "addr:full": "Murugankurichi, Palayamkottai, Tirunelveli", "addr:postcode": "627002", "addr:state": "Tamil Nadu", "amenity": "clinic", "healthcare": "clinic", "name": "Nellai Siddha Varma Consulting Centre", "source": "Local Knowledge"}}, {"type": "node", "id": 7847111697, "lat": 8.744868, "lon": 77.707455, "tags": {"addr:district": "Tirunelveli", "addr:postcode": "627001", "addr:state": "Tamil Nadu", "amenity": "hospital", "healthcare": "hospital", "name": "Dr. V. Ganapathi Sidha Hospital", "source": "Local Knowledge"}}, {"type": "node", "id": 7847111698, "lat": 8.7347909, "lon": 77.7216635, "tags": {"addr:district": "Tirunelveli", "addr:full": "Vannarpet, Vannarpettai, Tirunelveli", "addr:postcode": "627003", "addr:state": "Tamil Nadu", "amenity": "clinic", "healthcare": "clinic", "name": "Vamsam Fertility Research Centre", "source": "Local Knowledge"}}, {"type": "node", "id": 7847111699, "lat": 8.7263444, "lon": 77.7383011, "tags": {"addr:district": "Tirunelveli", "addr:full": "Palayamkottai, Tirunelveli", "addr:postcode": "627002", "addr:state": "Tamil Nadu", "amenity": "clinic", "healthcare": "clinic", "name": "Bethel Clinic", "source": "Local Knowledge"}}, {"type": "node", "id": 7847111700, "lat": 8.7280028, "lon": 77.7200448, "tags": {"addr:district": "Tirunelveli", "addr:full": "Kailash Nagar, Vannarpettai, Tirunelveli", "addr:postcode": "627003", "addr:state": "Tamil Nadu", "amenity": "hospital", "healthcare": "hospital", "name": "SMS Hospital", "source": "Local Knowledge"}}, {"type": "node", "id": 7847111701, "lat": 8.7266679, "lon": 77.7248281, "tags": {"addr:district": "Tirunelveli", "addr:full": "Vannarpettai, Tirunelveli", "addr:postcode": "627009", "addr:state": "Tamil Nadu", "amenity": "clinic", "healthcare": "clinic", "name": "Dr. Pothilingam's Eye Clinic", "source": "Local Knowledge"}}, {"type": "node", "id": 7847111702, "lat": 8.7156536, "lon": 77.7321465, "tags": {"addr:district": "Tirunelveli", "addr:full": "Palayamkottai, Tirunelveli", "addr:postcode": "627007", "addr:state": "Tamil Nadu", "amenity": "clinic", "healthcare": "clinic", "name": "Sugarless Clinic", "source": "Local Knowledge"}}, {"type": "node", "id": 7847111703, "lat": 8.7268477, "lon": 77.7337584, "tags": {"addr:district": "Tirunelveli", "addr:full": "Palayamkottai, Tirunelveli", "addr:postcode": "627002", "addr:state": "Tamil Nadu", "amenity": "clinic", "healthcare": "clinic", "name": "Aruna Cardiac Care", "source": "Local Knowledge"}}, {"type": "node", "id": 7847111705, "lat": 8.7267662, "lon": 77.7351624, "tags": {"addr:district": "Tirunelveli", "addr:full": "Palayamkottai, Tirunelveli", "addr:postcode": "627002", "addr:state": "Tamil Nadu", "amenity": "clinic", "healthcare": "clinic", "name": "Muthamil Clinic", "source": "Local Knowledge"}}, {"type": "node", "id": 7847111706, "lat": 8.7440251, "lon": 77.7069745, "tags": {"addr:district": "Tirunelveli", "addr:full": "Thachanallur, Tirunelveli", "addr:postcode": "627001", "addr:state": "Tamil Nadu", "amenity": "clinic", "healthcare": "clinic", "name": "Geetharani Clinic", "source": "Local Knowledge"}}, {"type": "node", "id": 7847111707, "lat": 8.7160513, "lon": 77.7322389, "tags": {"addr:district": "Tirunelveli", "addr:full": "Palayamkottai, Tirunelveli", "addr:postcode": "627002", "addr:state": "Tamil Nadu", "amenity": "hospital", "healthcare": "hospital", "name": "V Care Hair Care Hospital", "source": "Local Knowledge"}}, {"type": "node", "id": 7847111708, "lat": 8.724229, "lon": 77.7313244, "tags": {"addr:district": "Tirunelveli", "addr:full": "Kokkirakulam, Tirunelveli", "addr:postcode": "627002", "addr:state": "Tamil Nadu", "amenity": "clinic", "healthcare": "clinic", "name": "Nellai Ayurveda Clinic", "source": "Local Knowledge"}}, {"type": "node", "id": 7847111709, "lat": 8.711325, "lon": 77.734088, "tags": {"addr:district": "Tirunelveli", "addr:full": "Palayamkottai, Tirunelveli", "addr:postcode": "627007", "addr:state": "Tamil Nadu", "amenity": "clinic", "healthcare": "clinic", "name": "Beulah Nursing Home", "source": "Local Knowledge"}}, {"type": "node", "id": 7847111710, "lat": 8.7231175, "lon": 77.7218894, "tags": {"addr:district": "Tirunelveli", "addr:full": "Vannarpettai, Tirunelveli", "addr:postcode": "627003", "addr:state": "Tamil Nadu", "amenity": "hospital", "healthcare": "hospital", "name": "Chendhur Cardiac Centre & Multi Speciality Hospital", "source": "Local Knowledge"}}, {"type": "node", "id": 7847111711, "lat": 8.7262854, "lon": 77.7328825, "tags": {"addr:district": "Tirunelveli", "addr:full": "Palayamkottai, Tirunelveli", "addr:postcode": "627002", "addr:state": "Tamil Nadu", "amenity": "hospital", "healthcare": "hospital", "name": "Gem Head and Neck Hospital", "source": "Local Knowledge"}}, {"type": "node", "id": 7847111712, "lat": 8.7259664, "lon": 77.7302128, "tags": {"addr:district": "Tirunelveli", "addr:full": "Murugankurichi, Palayamkottai, Tirunelveli", "addr:postcode": "627002", "addr:state": "Tamil Nadu", "amenity": "clinic", "healthcare": "clinic", "name": "Aruna Siddha Clinic", "source": "Local Knowledge"}}, {"type": "node", "id": 7847111713, "lat": 8.7250197, "lon": 77.7374832, "tags": {"addr:district": "Tirunelveli", "addr:full": "Palayamkottai, Tirunelveli", "addr:postcode": "627002", "addr:state": "Tamil Nadu", "amenity": "clinic", "healthcare": "clinic", "name": "Laxmi Bali Clinic", "source": "Local Knowledge"}}, {"type": "node", "id": 7847111714, "lat": 8.7489004, "lon": 77.7031702, "tags": {"addr:district": "Tirunelveli", "addr:full": "Tirunelveli", "addr:postcode": "627358", "addr:state": "Tamil Nadu", "amenity": "doctors", "healthcare": "doctor", "name": "Dr. RL Balan", "source": "Local Knowledge"}}, {"type": "node", "id": 7847111715, "lat": 8.715862, "lon": 77.732183, "tags": {"addr:district": "Tirunelveli", "addr:full": "Palayamkottai, Tirunelveli", "addr:postcode": "627002", "addr:state": "Tamil Nadu", "amenity": "hospital", "healthcare": "hospital", "name": "Allapitchi Siddha Hospital", "source": "Local Knowledge"}}, {"type": "node", "id": 7847111716, "lat": 8.7138377, "lon": 77.7322929, "tags": {"addr:district": "Tirunelveli", "addr:full": "Palayamkottai, Tirunelveli", "addr:postcode": "627007", "addr:state": "Tamil Nadu", "amenity": "clinic", "healthcare": "clinic", "name": "Dr. Vaikundaraman Clinic", "source": "Local Knowledge"}}, {"type": "node", "id": 7847111717, "lat": 8.7415457, "lon": 77.7137908, "tags": {"addr:district": "Tirunelveli", "addr:full": "Balabagya Nagar, Tirunelveli", "addr:postcode": "627001", "addr:state": "Tamil Nadu", "amenity": "clinic", "healthcare": "clinic", "name": "Southern Heart Centre", "source": "Local Knowledge"}}, {"type": "node", "id": 7847111719, "lat": 8.7262063, "lon": 77.7320552, "tags": {"addr:district": "Tirunelveli", "addr:full": "Palayamkottai, Tirunelveli", "addr:postcode": "627002", "addr:state": "Tamil Nadu", "amenity": "clinic", "healthcare": "clinic", "name": "Hosanna Clinic", "source": "Local Knowledge"}}, {"type": "node", "id": 7847111720, "lat": 8.7254466, "lon": 77.7308309, "tags": {"addr:district": "Tirunelveli", "addr:full": "Tirunelveli", "addr:postcode": "627002", "addr:state": "Tamil Nadu", "amenity": "clinic", "healthcare": "clinic", "name": "Dr. Alagesan Neuro Clinic", "source": "Local Knowledge"}}, {"type": "node", "id": 7847111721, "lat": 8.7287561, "lon": 77.7404281, "tags": {"addr:district": "Tirunelveli", "addr:full": "Palayamkottai, Tirunelveli", "addr:postcode": "627002", "addr:state": "Tamil Nadu", "amenity": "hospital", "healthcare": "hospital", "name": "Mangala Hospital", "source": "Local Knowledge"}}, {"type": "node", "id": 7847111722, "lat": 8.7188786, "lon": 77.7319995, "tags": {"addr:district": "Tirunelveli", "addr:full": "Palayamkottai, Tirunelveli", "addr:postcode": "627002", "addr:state": "Tamil Nadu", "amenity": "clinic", "healthcare": "clinic", "name": "Raa-Shak Dental & Orthodontic Clinic", "source": "Local Knowledge"}}, {"type": "node", "id": 7847111723, "lat": 8.725633, "lon": 77.7334481}, {"type": "node", "id": 7847111724, "lat": 8.728457, "lon": 77.731351, "tags": {"addr:district": "Tirunelveli", "addr:full": "Thimmarajapuram, Tirunelveli", "addr:postcode": "627002", "addr:state": "Tamil Nadu", "amenity": "clinic", "healthcare": "clinic", "name": "John Acupuncture Center", "source": "Local Knowledge"}}, {"type": "node", "id": 7847111725, "lat": 8.7218492, "lon": 77.7319473, "tags": {"addr:district": "Tirunelveli", "addr:full": "Palayamkottai, Tirunelveli", "addr:postcode": "627002", "addr:state": "Tamil Nadu", "amenity": "clinic", "healthcare": "clinic", "name": "Queens Fertility Centre", "source": "Local Knowledge"}}, {"type": "node", "id": 7847111726, "lat": 8.7222602, "lon": 77.7317495, "tags": {"addr:district": "Tirunelveli", "addr:full": "Palayamkottai, Tirunelveli", "addr:postcode": "627002", "addr:state": "Tamil Nadu", "amenity": "clinic", "healthcare": "clinic", "name": "Dr. Sathyas Dental and ENT Clinic", "source": "Local Knowledge"}}, {"type": "node", "id": 7847111727, "lat": 8.7237352, "lon": 77.7336022, "tags": {"addr:district": "Tirunelveli", "addr:full": "Palayamkottai, Tirunelveli", "addr:postcode": "627002", "addr:state": "Tamil Nadu", "amenity": "clinic", "healthcare": "clinic", "name": "Guru Clinic", "source": "Local Knowledge"}}, {"type": "node", "id": 7847111728, "lat": 8.7249417, "lon": 77.7336773, "tags": {"addr:district": "Tirunelveli", "addr:full": "Palayamkottai, Tirunelveli", "addr:postcode": "627002", "addr:state": "Tamil Nadu", "amenity": "clinic", "healthcare": "clinic", "name": "Meera Homeo Clinic", "source": "Local Knowledge"}}, {"type": "node", "id": 7847111729, "lat": 8.7280357, "lon": 77.7236177, "tags": {"addr:district": "Tirunelveli", "addr:full": "Vannarpettai, Tirunelveli", "addr:postcode": "627002", "addr:state": "Tamil Nadu", "amenity": "clinic", "healthcare": "clinic", "name": "AKJN Skin and Laser Centre", "source": "Local Knowledge"}}, {"type": "node", "id": 7847111730, "lat": 8.7255734, "lon": 77.7305734, "tags": {"addr:district": "Tirunelveli", "addr:full": "Murugankurichi, Palayamkottai, Tirunelveli", "addr:postcode": "627002", "addr:state": "Tamil Nadu", "amenity": "clinic", "healthcare": "clinic", "name": "Sree Velsanth Cancer Care Centre", "source": "Local Knowledge"}}, {"type": "node", "id": 7847111731, "lat": 8.7259078, "lon": 77.7360784, "tags": {"addr:district": "Tirunelveli", "addr:full": "Palayamkottai, Tirunelveli", "addr:postcode": "627002", "addr:state": "Tamil Nadu", "amenity": "clinic", "healthcare": "clinic", "name": "Ram Barath Polyclinic", "source": "Local Knowledge"}}, {"type": "node", "id": 7847111732, "lat": 8.74888, "lon": 77.699599, "tags": {"addr:district": "Tirunelveli", "addr:full": "Tirunelveli", "addr:postcode": "627358", "addr:state": "Tamil Nadu", "amenity": "clinic", "healthcare": "clinic", "name": "Jeya Lakshmy Clinic", "source": "Local Knowledge"}}, {"type": "node", "id": 7847111733, "lat": 8.7269228, "lon": 77.733596, "tags": {"addr:district": "Tirunelveli", "addr:full": "Palayamkottai, Tirunelveli", "addr:postcode": "627002", "addr:state": "Tamil Nadu", "amenity": "hospital", "healthcare": "hospital", "name": "P.S. Hospital", "source": "Local Knowledge"}}, {"type": "node", "id": 7847111734, "lat": 8.729731, "lon": 77.7244314, "tags": {"addr:district": "Tirunelveli", "addr:full": "Vannavpattai, Barani Nagar, Tirunelveli", "addr:postcode": "627003", "addr:state": "Tamil Nadu", "amenity": "clinic", "healthcare": "clinic", "name": "Asukavi Acupuncture Centre", "source": "Local Knowledge"}}, {"type": "node", "id": 7847111735, "lat": 8.733051, "lon": 77.722927, "tags": {"addr:district": "Tirunelveli", "addr:full": "Vannarpettai, Tirunelveli", "addr:postcode": "627003", "addr:state": "Tamil Nadu", "amenity": "hospital", "healthcare": "hospital", "name": "Thanvanthri Hospital", "source": "Local Knowledge"}}, {"type": "node", "id": 7847111736, "lat": 8.7191315, "lon": 77.7327122, "tags": {"addr:district": "Tirunelveli", "addr:full": "Palayamkottai, Tirunelveli", "addr:postcode": "627002", "addr:state": "Tamil Nadu", "amenity": "clinic", "healthcare": "clinic", "name": "Dr. Elangovan Chellapa Ortho Clinic", "source": "Local Knowledge"}}, {"type": "node", "id": 7847111737, "lat": 8.725894, "lon": 77.7309166, "tags": {"addr:district": "Tirunelveli", "addr:full": "Murugankurichi, Palayamkottai, Tirunelveli", "addr:postcode": "627002", "addr:state": "Tamil Nadu", "amenity": "doctors", "healthcare": "doctor", "name": "Dr. Mohammed Thampy", "source": "Local Knowledge"}}, {"type": "node", "id": 7847111738, "lat": 8.7442121, "lon": 77.7044254, "tags": {"addr:district": "Tirunelveli", "addr:full": "Thachanallur, Tirunelveli", "addr:postcode": "627001", "addr:state": "Tamil Nadu", "amenity": "hospital", "healthcare": "hospital", "name": "Adamali Hosptial", "source": "Local Knowledge"}}, {"type": "node", "id": 7847111739, "lat": 8.719595, "lon": 77.731876, "tags": {"addr:district": "Tirunelveli", "addr:full": "Kattnayakan, Palayamkottai, Tirunelveli", "addr:postcode": "627002", "addr:state": "Tamil Nadu", "amenity": "hospital", "healthcare": "hospital", "name": "Muthu Damian Hospital", "source": "Local Knowledge"}}, {"type": "node", "id": 7847111740, "lat": 8.726895, "lon": 77.7336814, "tags": {"addr:district": "Tirunelveli", "addr:full": "Palayamkottai, Tirunelveli", "addr:postcode": "627002", "addr:state": "Tamil Nadu", "amenity": "hospital", "healthcare": "hospital", "name": "Paul Hospital", "source": "Local Knowledge"}}, {"type": "node", "id": 7847111741, "lat": 8.7303047, "lon": 77.7228248, "tags": {"addr:district": "Tirunelveli", "addr:full": "Barani Nagar, Tirunelveli", "addr:postcode": "627003", "addr:state": "Tamil Nadu", "amenity": "hospital", "healthcare": "hospital", "name": "Nivya Hospitals", "source": "Local Knowledge"}}, {"type": "node", "id": 7847111742, "lat": 8.7257127, "lon": 77.730661, "tags": {"addr:district": "Tirunelveli", "addr:full": "Palayamkottai, Tirunelveli", "addr:postcode": "627002", "addr:state": "Tamil Nadu", "amenity": "hospital", "healthcare": "hospital", "name": "Thambi Hospital Skin Specialist", "source": "Local Knowledge"}}, {"type": "node", "id": 7847111743, "lat": 8.7445005, "lon": 77.7118931, "tags": {"addr:district": "Tirunelveli", "addr:full": "Gomathy Nagar, Tirunelveli", "addr:postcode": "627001", "addr:state": "Tamil Nadu", "amenity": "clinic", "healthcare": "clinic", "name": "Dr. Radhakrishnan Clinic", "source": "Local Knowledge"}}, {"type": "node", "id": 7847111744, "lat": 8.7272665, "lon": 77.7362323, "tags": {"addr:district": "Tirunelveli", "addr:full": "Palayamkottai, Tirunelveli", "addr:postcode": "627002", "addr:state": "Tamil Nadu", "amenity": "clinic", "healthcare": "clinic", "name": "Siva Counselling Clinic", "source": "Local Knowledge"}}, {"type": "node", "id": 7847111745, "lat": 8.7252868, "lon": 77.7310956, "tags": {"addr:district": "Tirunelveli", "addr:full": "Murugankurichi, Palayamkottai, Tirunelveli", "addr:postcode": "627002", "addr:state": "Tamil Nadu", "amenity": "clinic", "healthcare": "clinic", "name": "Dr.K. Muthurajan Malar Homeo Clinic", "source": "Local Knowledge"}}, {"type": "node", "id": 7847111746, "lat": 8.7292235, "lon": 77.7229644, "tags": {"addr:district": "Tirunelveli", "addr:full": "Barani Nagar, Tirunelveli", "addr:postcode": "627003", "addr:state": "Tamil Nadu", "amenity": "clinic", "healthcare": "clinic", "name": "Sankar Neuro Clinic", "source": "Local Knowledge"}}, {"type": "node", "id": 7847111747, "lat": 8.7300726, "lon": 77.7195355, "tags": {"addr:district": "Tirunelveli", "addr:full": "Kailash Nagar, Vannarpettai, Tirunelveli", "addr:postcode": "627003", "addr:state": "Tamil Nadu", "amenity": "clinic", "healthcare": "clinic", "name": "Hari Fertility Centre", "source": "Local Knowledge"}}, {"type": "node", "id": 8130521379, "lat": 8.6949575, "lon": 77.7291371, "tags": {"amenity": "clinic", "healthcare": "clinic", "name": "Leela Clinic"}}, {"type": "node", "id": 8725827858, "lat": 8.7525253, "lon": 77.7036702, "tags": {"amenity": "hospital", "healthcare": "hospital"}}, {"type": "node", "id": 9195829245, "lat": 8.7241333, "lon": 77.6639981, "tags": {"amenity": "hospital", "healthcare": "hospital", "name": "Dr. Sivaraman Hospital"}}, {"type": "node", "id": 9774581143, "lat": 8.6986731, "lon": 77.7284353}, {"type": "node", "id": 9774581144, "lat": 8.6986269, "lon": 77.7285742}, {"type": "node", "id": 9774581145, "lat": 8.6988031, "lon": 77.7286107}, {"type": "node", "id": 9774581146, "lat": 8.6988464, "lon": 77.7284777}, {"type": "node", "id": 9865083472, "lat": 8.7200481, "lon": 77.771424, "tags": {"addr:city": "Tirunelveli", "addr:postcode": "627011", "addr:street": "KTC Nagar", "amenity": "clinic", "healthcare": "clinic", "name": "Crescent Multicate Clinic"}}, {"type": "node", "id": 9919653558, "lat": 8.7264532, "lon": 77.6657907, "tags": {"addr:city": "Tirunelveli", "addr:housenumber": "503, 504", "addr:street": "Cheranmahadevi Road", "amenity": "hospital", "name": "Masthan Hospital", "opening_hours": "Mo-Sa 09:00-21:00; Su 08:30-14:30", "phone": "0462-2342323"}}, {"type": "node", "id": 9922001981, "lat": 8.7261253, "lon": 77.6612754}, {"type": "node", "id": 9950716794, "lat": 8.6994964, "lon": 77.7098482, "tags": {"amenity": "hospital", "name": "Nellai Multicare Clinic", "phone": "8682893234", "website": "https://www.nellaicrescent.com/"}}, {"type": "node", "id": 10009237141, "lat": 8.7257974, "lon": 77.7320373}, {"type": "node", "id": 10009237142, "lat": 8.7248059, "lon": 77.7319193}, {"type": "node", "id": 10009237143, "lat": 8.7246574, "lon": 77.7319676}, {"type": "node", "id": 10009237144, "lat": 8.7242756, "lon": 77.7324986}, {"type": "node", "id": 10009237145, "lat": 8.7235174, "lon": 77.7333462}, {"type": "node", "id": 10009237146, "lat": 8.7235916, "lon": 77.733432}, {"type": "node", "id": 10803942066, "lat": 8.6956572, "lon": 77.7332534, "tags": {"amenity": "doctors", "name": "Hebron councelling centre"}}, {"type": "node", "id": 11434292036, "lat": 8.7260024, "lon": 77.6613508}, {"type": "node", "id": 11434292455, "lat": 8.7260095, "lon": 77.6612656}, {"type": "node", "id": 11434294594, "lat": 8.7261182, "lon": 77.6613607}, {"type": "node", "id": 12536345242, "lat": 8.7272908, "lon": 77.7173787, "tags": {"amenity": "hospital", "check_date": "2025-01-27", "healthcare": "hospital", "name": "The Eye Foundation Eye Hospital", "source": "survey"}}, {"type": "way", "id": 204553710, "nodes": [2145507579, 2145507518, 2145507548, 2145507613, 2145507579], "tags": {"addr:district": "Tirunelveli", "addr:full": "# 8,9,10 Sivapuram Street, Tirunelveli Junction", "addr:postcode": "627001", "addr:state": "Tamil Nadu", "amenity": "hospital", "emergency": "yes", "healthcare": "hospital", "name": "R S P Cardio Thoracic Research Centre", "source": "OpenGovernmentData"}}, {"type": "way", "id": 204555695, "nodes": [2145525088, 2145524951, 2145525157, 2145525173, 2145525002, 2145525120, 2145525029, 2145525088], "tags": {"addr:district": "Tirunelveli", "addr:full": "Madras Road, Opposite Ram Theatre", "addr:postcode": "627001", "addr:state": "Tamil Nadu", "amenity": "hospital", "healthcare": "hospital", "name": "Lakshmi Hospitals, Tirunelveli", "source": "OpenGovernmentData"}}, {"type": "way", "id": 382425891, "nodes": [3856203582, 3856203583, 3856203584, 3856203586, 3856203587, 3856203588, 3856203589, 3856203582], "tags": {"addr:city": "Tirunelveli", "addr:district": "Tirunelveli", "addr:full": "10/3, South Bye- Pass Road, Vannarpettai", "addr:postcode": "627003", "addr:state": "Tamil Nadu", "addr:street": "South Bypass Road", "amenity": "hospital", "healthcare": "hospital", "name": "Rosemary Mission Hospitals", "source": "OpenGovernmentData"}}, {"type": "way", "id": 1064288887, "nodes": [9774581143, 9774581144, 9774581145, 9774581146, 9774581143], "tags": {"addr:city": "Tirunelveli", "addr:housenumber": "90", "addr:postcode": "627007", "addr:street": "Raja Rajeshwari Nagar", "amenity": "clinic", "building": "yes", "healthcare": "clinic", "healthcare:speciality": "ear;nose;throat", "name": "Sri Annai ENT Clinic", "name:ta": "\u0bb6\u0bcd\u0bb0\u0bc0 \u0b85\u0ba9\u0bcd\u0ba9\u0bc8 \u0b95\u0bbe\u0bae\u0bc2\u0ba4\u0bca \u0b95\u0bcd\u0bb3\u0bbf\u0ba9\u0bbf"}}, {"type": "way", "id": 1092912286, "nodes": [7847111723, 10009237146, 10009237145, 10009237144, 10009237143, 10009237142, 10009237141, 7847111723], "tags": {"addr:district": "Tirunelveli", "addr:full": "Murugankurichi, Palayamkottai, Tirunelveli", "addr:postcode": "627002", "addr:state": "Tamil Nadu", "amenity": "hospital", "healthcare": "hospital", "name": "Government Siddha Medical College and Hospital", "source": "Local Knowledge"}}, {"type": "way", "id": 1232607314, "nodes": [11434292036, 11434294594, 9922001981, 11434292455, 11434292036], "tags": {"addr:street": "Bharathar South Street", "amenity": "clinic", "building": "yes", "name": "Gandhiji Iyarkai Maruthuva Manai", "source": "microsoft/BuildingFootprints"}}]}